Workbook

Sheet Project Info
B2: PROJECT INFORMATION
B4: Edit values in column C. The Cover and Appendix Cover tabs display them.
B6: Project Name | C6: Qiddiya D-18 - TSE Irrigation Storage Tanks (RFP-027)
B7: Client | C7: Qiddiya Investment Company
B8: Address | C8: Qiddiya, Riyadh, Kingdom of Saudi Arabia
B9: Contract Reference | C9: QPMO-410-CT-05958
B10: Contractor | C10: SAMA Construction
B11: Engineer | C11: KEO International Consultants
B12: Cost Consultant | C12: WT Partnership
B13: Document Title | C13: Cost Assessment of the Contractor's Proposal - TSE Irrigation Storage Tanks (RFP-027) - Rev 02
B14: Document Date | C14: 30-Sep-2026
B15: Document Reference | C15: RFP-027 / SAMACO-RRFP-000001
B16: Appendix Letter | C16: A
B17: Appendix Description | C17: Cost Assessment of the Contractor's Proposal - TSE Irrigation Storage Tanks (RFP-027)
B18: Cover Subtitle (auto) | C18: =C13 & " | " & C14 -> Cost Assessment of the Contractor's Proposal - TSE Irrigation Storage Tanks (RFP-027) - Rev 02 | 30-Sep-2026
B19: Cover Reference (auto) | C19: ="Reference: " & C15 -> Reference: RFP-027 / SAMACO-RRFP-000001
B20: Appendix Title (auto) | C20: ="Appendix " & C16 -> Appendix A

Sheet Cover

Sheet Appendix Cover

Sheet Assessment
A1: COST ASSESSMENT OF THE CONTRACTOR'S PROPOSAL
A2: TSE Irrigation Storage Tanks and Associated Pipeworks (RFP-027) - Contract QPMO-410-CT-05958
A3: Contractor: SAMA Construction | Engineer: KEO | Cost Consultant: WT Partnership | Rev 02, 30-Sep-2026
A4: ="Purpose: to value the Contractor's revised proposal ref. SAMACO-RRFP-000001 dated 13-Aug-2026 for the 2 No. TSE irrigation storage tanks, dismantling of damaged Tank-1, associated pipework and testing. Result: the proposal of SAR " & TEXT(F21,"#,##0.00") & " is assessed at SAR " & TEXT(K21,"#,##0.00") & ", both excluding VAT (row 21). Basis: supplier quotations where the Contractor obtained them (Items 3 and 6), first-principles build-ups elsewhere ('Build-Up' tab), with every time-related period taken from the Contractor's programme of 29-"&"Sep-2026 ('Programme' tab) - a programme under the Engineer's approval, not an agreed basis. Status: preliminary - items marked Provisional depend on confirmations still outstanding. Rev 02 replaces Rev 01 dated 17-Sep-2026 (SAR " & TEXT(6921685.64,"#,##0.00") & ")." -> Purpose: to value the Contractor's revised proposal ref. SAMACO-RRFP-000001 dated 13-Aug-2026 for the 2 No. TSE irrigation storage tanks, dismantling of damaged Tank-1, associated pipework and testing. Result: the proposal of SAR 8,110,296.62 is assessed at SAR 6,984,428.39, both excluding VAT (row 21). Basis: supplier quotations where the Contractor obtained them (Items 3 and 6), first-principles build-ups elsewhere ('Build-Up' tab), with every time-related period taken from the Contractor's programme of 29-Sep-2026 ('Programme' tab) - a programme under the Engineer's approval, not an agreed basis. Status: preliminary - items marked Provisional depend on confirmations still outstanding. Rev 02 replaces Rev 01 dated 17-Sep-2026 (SAR 6,921,685.64).
C5: CONTRACTOR'S PROPOSAL - SAMACO-RRFP-000001, 13-AUG-2026, AS SUBMITTED | H5: ASSESSMENT | O5: VARIANCE
A6: Item | B6: Description | C6: Unit | D6: Qty | E6: Rate (SAR) | F6: Amount (SAR) | G6: Substantiation submitted | H6: Unit | I6: Qty | J6: Rate (SAR) | K6: Amount (SAR) | L6: Assessment | M6: Basis of rate | N6: Status | O6: Variance (SAR) | P6: Variance %
A7: GENERAL ITEMS
A8: 1 | B8: Site Mobilization and Demobilization; Site Temporary Facilities, Welfare, Personnel, and Resources (Stand Alone) | C8: LS | D8: 1 | E8: 680000 | F8: 680000 | G8: Percentage allocation of the lump sum; no quantities or rates. See 'Build-Up Comparison' | H8: LS | I8: 1 | J8: ='Build-Up'!$F$32 -> 319680.56 | K8: =I8*J8 -> 319680.56 | L8: Separate site establishment: the tank site is in the lower plateau, outside the D-18 boundary, so site staff, welfare, water, security, insurance endorsement, mobilisation, demobilisation and close-out are assessed for the site period derived from the Contractor's programme of 29-Sep-2026 ('Programme' tab, D1): mobilisation on 22-Aug-2026 to the end of demobilisation, the end being set by the external readiness milestone of 03-Dec-2026 and the tie-in, sequential testing, commissioning and demobilisation that follow; site staff are assessed role by role by phase ('Programme' tab, Section 4). Design resources are shared with the main Contract. See 'Build-Up' Item 1, 'Programme' Sections 3 to 5 and 'Build-Up Comparison' Section 3. | M8: Star Rate | N8: Assessed | O8: =F8-K8 -> 360319.44 | P8: =IF(K8=0,"",(F8-K8)/K8) -> 1.1271234
A9: DESIGN AND ENGINEERING
A10: 2 | B10: Design and Engineering works | C10: LS | D10: 1 | E10: 85000 | F10: 85000 | G10: None | H10: LS | I10: 1 | J10: ='Build-Up'!$F$41 -> 55000 | K10: =I10*J10 -> 55000 | L10: Assessed build-up; tank design sits with the supplier. See 'Build-Up' Item 2. | M10: Star Rate | N10: Assessed | O10: =F10-K10 -> 30000 | P10: =IF(K10=0,"",(F10-K10)/K10) -> 0.54545455
A11: SITE WORKS
A12: 3 | B12: Safe Dismantling & Removal from Site of Damaged TSE Tank - 1 | C12: Ls | D12: 1 | E12: 71000 | F12: 71000 | G12: Supplier quotation Al Mousa S04647 dated 10-Aug-2026 | H12: Ls | I12: 1 | J12: ='Build-Up'!$F$47 -> 71000 | K12: =I12*J12 -> 71000 | L12: Lowest of the Contractor's three quotations, adopted for dismantling, segregation and loading only on the scope recorded in the previous revision; the quotation itself is not attached to this revision and its scope split is not yet confirmed in writing. Haulage and handover are Item 4. See 'Build-Up' Item 3. | M12: Market Tested | N12: Provisional - scope confirmation | O12: =F12-K12 -> 0 | P12: =IF(K12=0,"",(F12-K12)/K12) -> 0
A13: 4 | B13: Removal and Disposal of Damaged TSE Tank to Approved Landfill | C13: LS | D13: 1 | E13: 10500 | F13: 10500 | G13: None | H13: LS | I13: 1 | J13: ='Build-Up'!$F$69 -> 6300 | K13: =I13*J13 -> 6300 | L13: Haulage only. The Engineer's (KEO) email of 30-Aug-2026: materials are handed to the Employer locally, so no disposal or tipping applies. Location and rate to be confirmed. See 'Build-Up' Item 4. | M13: Star Rate | N13: Provisional - handover location | O13: =F13-K13 -> 4200 | P13: =IF(K13=0,"",(F13-K13)/K13) -> 0.66666667
A14: 5 | B14: Temporary Works, Construction Equipment, Tools and Site Support Facilities (Scaffolding, cranes, boom trucks, generators, trucks, small tools, temporary facilities and other equipment/resources required for execution of the works.) | C14: Ls | D14: 1 | E14: 504192.02 | F14: 504192.02 | G14: Percentage allocation of the lump sum; no quantities or rates. See 'Build-Up Comparison' | H14: Ls | I14: 1 | J14: ='Build-Up'!$F$89 -> 325350 | K14: =I14*J14 -> 325350 | L14: Plant, access, power and supplier attendance that the tank quotation excludes; the supplier's price is supply and installation, so GRP erectors are not priced (recorded scope of the offer, to be confirmed against the original). Helpers and plant are assessed phase by phase on the 'Programme' tab, Section 4, from material availability and activity dependencies: one helper gang while only Tank 1 material is planned on site, a second only while two fronts run (22-Oct to 14-Nov-2026), attendance for the submitted durations. No plant schedule has been submitted. See 'Build-Up' Item 5, 'Programme' Sections 3 to 5 and 'Build-Up Comparison' Section 4. | M14: Star Rate | N14: Assessed | O14: =F14-K14 -> 178842.02 | P14: =IF(K14=0,"",(F14-K14)/K14) -> 0.54969116
A15: TANKS
A16: 6 | B16: Supply and install of hot pressed non-insulated panel tank size:34(17+17) m(l) x 30.0 m(w) x 4.0 m(h) total capacity:4080 m3 | C16: No | D16: 2 | E16: 2763500 | F16: 5527000 | G16: Supplier quotation Al Mousa S04488 dated 09-Jul-2026 with Stalwart technical offer SS-07-26-1516 dated 03-Aug-2026 | H16: No | I16: 2 | J16: ='Build-Up'!$F$95 -> 2763500 | K16: =I16*J16 -> 5527000 | L16: The Contractor's adopted lowest quotation at net supplier cost, before the 5 per cent Overhead and Profit. It prices an insulated tank; the Engineer's (KEO) email of 30-Aug-2026 is that insulation is not required, so a lower price is expected. Quotation lapsed 08-Aug-2026; base panels not confirmed. See 'Build-Up' Item 6. | M16: Market Tested | N16: Provisional - quotation and specification | O16: =F16-K16 -> 0 | P16: =IF(K16=0,"",(F16-K16)/K16) -> 0
A17: 7 | B17: Testing, Commissioning, Hydrostatic/Leak Testing, System Integration and Handover | C17: Ls | D17: 2 | E17: 213200 | F17: 426400 | G17: Percentage allocation of the lump sum; no quantities or rates. See 'Build-Up Comparison' | H17: Ls | I17: 2 | J17: ='Build-Up'!$F$124 -> 51153 | K17: =I17*J17 -> 102306 | L17: One tank filled and the water re-used for the second, per the Engineer's (KEO) email of 30-Aug-2026; the Contractor's programme tests both tanks in parallel, which is shown beside this basis on the 'Programme' tab and not carried; the sequential test is fitted to the programme there, with Tank 1 tested early on a conditional method assumption and integrated commissioning after both tanks have passed and the tie-in is complete. A third-party factory acceptance test the Contractor is arranging is carried at nil (line 7.23) pending evidence that the Engineer requires it. Excludes the supplier's leak-test supervision (Item 6) and re-testing, which is the Contractor's obligation. Water source to be confirmed. See 'Build-Up' Item 7. | M17: Star Rate | N17: Provisional - water source and testing basis | O17: =F17-K17 -> 324094 | P17: =IF(K17=0,"",(F17-K17)/K17) -> 3.1678885
A18: 8 | B18: Supply, Fabrication and Installation of all Required TSE Tank Inlet/Outlet Piping, Instrumentation Connections, Supports and Accessories | C18: LS | D18: 1 | E18: 420000 | F18: 420000 | G18: Percentage allocation of the lump sum; no quantities or rates. See 'Build-Up Comparison' | H18: LS | I18: 1 | J18: ='Build-Up'!$F$150 -> 245200 | K18: =I18*J18 -> 245200 | L18: Provisional allowance priced to the RFP specification (GRP or ductile iron above DN150, uPVC below, butterfly isolation valves). The Contractor's procurement tracker of 29-Sep-2026 shows HDPE main-line pipe, a gate valve and a motorised butterfly valve being procured; the substitutions are not approved and are shown for information after line 8.21. No quantities exist: the pipework shop drawings were returned Code C and no take-off has been received. See 'Build-Up' Item 8. | M18: Star Rate | N18: Provisional - take-off pending | O18: =F18-K18 -> 174800 | P18: =IF(K18=0,"",(F18-K18)/K18) -> 0.71288744
B19: SUBTOTAL (SAR), VAT excluded | F19: =SUM(F8:F18) -> 7724092 | K19: =SUM(K8:K18) -> 6651836.6 | O19: =F19-K19 -> 1072255.5 | P19: =IF(K19=0,"",(F19-K19)/K19) -> 0.1611969
B20: Overhead and Profit, 5 per cent | F20: 386204.6 | K20: =ROUND(K19*0.05,2) -> 332591.83 | L20: 5 per cent as the Contractor's submission, within the Bill of Quantities Preamble cap. Covers head-office overheads (management, administration, finance, procurement) and profit only. Site staff, welfare, plant, power, water, security, insurance endorsement and close-out are priced in the items, whether one site or two. | O20: =F20-K20 -> 53612.77 | P20: =IF(K20=0,"",(F20-K20)/K20) -> 0.16119689
B21: TOTAL (SAR), VAT excluded | F21: =F19+F20 -> 8110296.6 | K21: =K19+K20 -> 6984428.4 | O21: =F21-K21 -> 1125868.2 | P21: =IF(K21=0,"",(F21-K21)/K21) -> 0.1611969
A22: Contractor columns are as submitted and unchanged. Assessed rates in column J are calculated on the 'Build-Up' tab; quantities are those submitted. Status 'Provisional' marks an item that depends on a confirmation still outstanding; the list is on the 'Build-Up Comparison' tab, Section 7. The Contractor's programme of 29-Sep-2026 is under the Engineer's approval and is not an agreed basis; the Contractor has been instructed and is on site, the instruction reference not having been supplied to the Cost Consultant.
A23: This assessment is preliminary. It establishes a reasonable commercial provision on the information available at 30-Sep-2026 and does not constitute agreement of the final Variation value.
A24: ="Changes from Rev 01 dated 17-Sep-2026 (SAR 6,921,685.64): every time-related period re-based from an assumed 3-month site period to the Contractor's programme of 29-Sep-2026 - site staff by role and phase and facilities for the site period "&"to the end of demobilisation (Item 1 and the generators in Item 5), helpers and plant from a phase-by-phase resource matrix built on material availability and activity dependencies, access equipment on the erection windows (Item 5); Item 7 "&"re-sequenced with the Engineer's sequential basis carried, commissioning staff reconciled to that sequence and a nil line added for the third-party factory test; sealant tools and fixings provisionally excluded as within the recorded Item 6"&" scope and third-party inspection visits removed as not required (5.12, 5.13, 7.12); PPE, survey and document control increased on the programme evidence (1.18, 2.3, 2.4); every line linked to its activities or site service on the 'Programm"&"e' tab; Item 8 re-described to the RFP specification with the Contractor's procured materials shown alongside; the Contractor's cost loading, cash flow and manpower histogram recorded as evidence on the 'Build-Up Comparison' tab. No rate ha"&"s moved. Net effect: SAR " & TEXT(K21-6921685.64,"#,##0.00;-#,##0.00") & " (" & TEXT((K21-6921685.64)/6921685.64,"0.0%;-0.0%") & ")." -> Changes from Rev 01 dated 17-Sep-2026 (SAR 6,921,685.64): every time-related period re-based from an assumed 3-month site period to the Contractor's programme of 29-Sep-2026 - site staff by role and phase and facilities for the site period to the end of demobilisation (Item 1 and the generators in Item 5), helpers and plant from a phase-by-phase resource matrix built on material availability and activity dependencies, access equipment on the erection windows (Item 5); Item 7 re-sequenced with the Engineer's sequential basis carried, commissioning staff reconciled to that sequence and a nil line added for the third-party factory test; sealant tools and fixings provisionally excluded as within the recorded Item 6 scope and third-party inspection visits removed as not required (5.12, 5.13, 7.12); PPE, survey and document control increased on the programme evidence (1.18, 2.3, 2.4); every line linked to its activities or site service on the 'Programme' tab; Item 8 re-described to the RFP specification with the Contractor's procured materials shown alongside; the Contractor's cost loading, cash flow and manpower histogram recorded as evidence on the 'Build-Up Comparison' tab. No rate has moved. Net effect: SAR 62,742.75 (0.9%).

Sheet Build-Up
A1: ASSESSED RATE BUILD-UPS
A2: TSE Irrigation Storage Tanks and Associated Pipeworks (RFP-027) - Contract QPMO-410-CT-05958
A3: Contractor: SAMA Construction | Engineer: KEO | Cost Consultant: WT Partnership | Rev 02, 30-Sep-2026
A4: How to read this tab: each item on the 'Assessment' tab whose rate is assessed rather than quoted is built up here as quantity x rate, with its basis beside it. Item totals carry to column J of the 'Assessment' tab. Quantities shown in column D as links to the 'Programme' tab are derived from the Contractor's programme of 29-Sep-2026 on the basis carried there (Basis B); the same lines on the programme exactly as submitted (Basis A) are on the 'Programme' tab, Section 4. Rates marked 'assumption' are working assumptions pending the Contractor's substantiation. All amounts exclude VAT.
A6: ITEM 1 - SITE MOBILISATION, TEMPORARY FACILITIES AND WELFARE
A7: The tank site is in the lower plateau, outside the D-18 site boundary. Site management, welfare, water, security, insurance cover and close-out are therefore assessed as a separate establishment. Periods are taken from the Contractor's programme of 29-Sep-2026 ('Programme' tab, Section 3): site staff, transport and facilities for the site period D1, mobilisation to the end of demobilisation, with the post-demobilisation completion inspection priced at 1.22 and 1.23. The programme is under the Engineer's approval and is not an agreed basis; the end of the site period is set by the external readiness milestone of 03-Dec-2026 and the tie-in, sequential testing, commissioning and demobilisation that follow. Site staff are assessed role by role with their phase duties on the 'Programme' tab, Section 4. Design and engineering resources are shared with the main Contract (Item 2). Power is in Item 5. The tank supplier's price includes the installer's own mobilisation; the foundations and steel base frames are existing.
A8: Ref | B8: Description | C8: Unit | D8: Qty | E8: Rate (SAR) | F8: Amount (SAR) | G8: Basis
A9: 1.1 | B9: Site engineer - dedicated to the tank site | C9: month | D9: =Programme!$G$113 -> 4.1 | E9: 12000 | F9: =D9*E9 -> 49200 | G9: Dedicated for the site period, mobilisation to the end of demobilisation, with the phase duties set out on the 'Programme' tab, Section 4, role R1. Assessed market rate, Riyadh, Sep-2026 - assumption pending the Contractor's substantiation
A10: 1.2 | B10: HSE officer - dedicated | C10: month | D10: =Programme!$G$114 -> 4.1 | E10: 10000 | F10: =D10*E10 -> 41000 | G10: Dedicated for the site period with the phase duties at 'Programme' tab, Section 4, role R2. Assessed market rate, Riyadh, Sep-2026 - assumption pending the Contractor's substantiation
A11: 1.3 | B11: QA/QC inspector - dedicated (daily inspections, ITPs and WIRs during erection) | C11: month | D11: =Programme!$G$115 -> 3.7 | E11: 10000 | F11: =D11*E11 -> 37000 | G11: From the start of dismantling to completion of testing and commissioning only ('Programme' tab, Section 4, role R3); not during mobilisation or demobilisation. Assessed market rate, Riyadh, Sep-2026 - assumption pending the Contractor's substantiation
A12: 1.4 | B12: Works foreman - dedicated | C12: month | D12: =Programme!$G$116 -> 4.1 | E12: 8000 | F12: =D12*E12 -> 32800 | G12: Dedicated for the site period: the Contractor's own labour is on site from mobilisation to demobilisation ('Programme' tab, Section 4, role R4). Assessed market rate, Riyadh, Sep-2026 - assumption pending the Contractor's substantiation
A13: 1.5 | B13: Storekeeper / timekeeper | C13: month | D13: =Programme!$G$117 -> 3.3 | E13: 4000 | F13: =D13*E13 -> 13200 | G13: From the first delivery to completion of testing only ('Programme' tab, Section 4, role R5). Assessed market rate, Riyadh, Sep-2026 - assumption pending the Contractor's substantiation
A14: 1.6 | B14: Site office porta cabin, air-conditioned, rental with electricity connection and maintenance | C14: month | D14: =Programme!$G$118 -> 4.1 | E14: 2200 | F14: =D14*E14 -> 9020 | G14: Site period D1 on the 'Programme' tab, Section 3 (activity QCD18TSEMOB1250, 22-Aug-2026, to activity QCD18TSEDMOB1020, 24-Dec-2026). Assessed market rate, Riyadh, Sep-2026 - assumption pending the Contractor's substantiation
A15: 1.7 | B15: Rest and welfare porta cabin, air-conditioned, rental with electricity connection and maintenance | C15: month | D15: =Programme!$G$119 -> 4.1 | E15: 2200 | F15: =D15*E15 -> 9020 | G15: Site period D1 on the 'Programme' tab, Section 3 (activity QCD18TSEMOB1250, 22-Aug-2026, to activity QCD18TSEDMOB1020, 24-Dec-2026). Assessed market rate, Riyadh, Sep-2026 - assumption pending the Contractor's substantiation
A16: 1.8 | B16: WC unit, rental with servicing | C16: month | D16: =Programme!$G$120 -> 4.1 | E16: 1300 | F16: =D16*E16 -> 5330 | G16: Site period D1 on the 'Programme' tab, Section 3 (activity QCD18TSEMOB1250, 22-Aug-2026, to activity QCD18TSEDMOB1020, 24-Dec-2026). Assessed market rate, Riyadh, Sep-2026 - assumption pending the Contractor's substantiation
A17: 1.9 | B17: Site water supply - tankered deliveries for welfare and general site use, whole period | C17: delivery | D17: =Programme!$G$121 -> 36 | E17: 350 | F17: =D17*E17 -> 12600 | G17: Two 10 m3 deliveries a week for the weeks of the site period D1 on the 'Programme' tab, Section 3; no mains water at the tank site. Assessed market rate, Riyadh, Sep-2026 - assumption pending the Contractor's substantiation
A18: 1.10 | B18: Site water storage tank, hire | C18: month | D18: =Programme!$G$122 -> 4.1 | E18: 350 | F18: =D18*E18 -> 1435 | G18: Site period D1 on the 'Programme' tab, Section 3 (activity QCD18TSEMOB1250, 22-Aug-2026, to activity QCD18TSEDMOB1020, 24-Dec-2026). Assessed market rate, Riyadh, Sep-2026 - assumption pending the Contractor's substantiation
A19: 1.11 | B19: Storage containers, 2 No. for the panel storage window (RFP Scope of Works, work package 1 - pre-construction and setup: safe storage of panels) | C19: container-month | D19: =Programme!$G$123 -> 5.6 | E19: 1200 | F19: =D19*E19 -> 6720 | G19: 2 No. containers for the storage window D7 on the 'Programme' tab, Section 3, first delivery to the Tank 2 roof finish. Assessed market rate, Riyadh, Sep-2026 - assumption pending the Contractor's substantiation
A20: 1.12 | B20: Workforce transport to the tank site, daily bus | C20: month | D20: =Programme!$G$124 -> 4.1 | E20: 4000 | F20: =D20*E20 -> 16400 | G20: Separate site outside the D-18 boundary; site period D1 on the 'Programme' tab, Section 3. Assessed market rate, Riyadh, Sep-2026 - assumption pending the Contractor's substantiation
A21: 1.13 | B21: Watchman for the tank site | C21: month | D21: =Programme!$G$125 -> 4.1 | E21: 4500 | F21: =D21*E21 -> 18450 | G21: Site period D1 on the 'Programme' tab, Section 3. Included pending confirmation whether the Employer's security covers the lower plateau; delete if it does. Assessed market rate, Riyadh, Sep-2026 - assumption pending the Contractor's substantiation
A22: 1.14 | B22: Mobilisation - flatbed trips delivering cabins, containers and small plant | C22: trip | D22: 5 | E22: 1250 | F22: =D22*E22 -> 6250 | G22: 5 trips retained: the programme gives no trip count (activity QCD18TSEMOB1240, mobilisation, 5 working days). Assessed market rate, Riyadh, Sep-2026 - assumption pending the Contractor's substantiation
A23: 1.15 | B23: Demobilisation - flatbed trips removing cabins, containers and small plant | C23: trip | D23: 5 | E23: 1250 | F23: =D23*E23 -> 6250 | G23: 5 trips retained: the programme gives no trip count (activity QCD18TSEDMOB1020, demobilisation, 7 working days). Assessed market rate, Riyadh, Sep-2026 - assumption pending the Contractor's substantiation
A24: 1.16 | B24: Site clean-up on demobilisation, 4 No. x 3 days | C24: man-day | D24: 12 | E24: 150 | F24: =D24*E24 -> 1800 | G24: Assessed market rate, Riyadh, Sep-2026 - assumption pending the Contractor's substantiation
A25: 1.17 | B25: Insurance endorsement - extension of the Contractor's All Risks and third-party liability cover to the tank site | C25: item | D25: 1 | E25: 13000 | F25: =D25*E25 -> 13000 | G25: The Contract insurances cover the Site as defined; the tank site is outside it. Assumed at 0.2 per cent of the works value - the insurer's endorsement premium is to be substantiated by the Contractor
A26: 1.18 | B26: Personal protective equipment, full sets | C26: No | D26: 20 | E26: 350 | F26: =D26*E26 -> 7000 | G26: Peak Contractor headcount from the resource matrix ('Programme' tab, Section 4): two helper gangs and the offloading gang (up to 14), five site staff and the pipework crew - about 20 sets; the supplier's crews wear their own. Assessed market rate, Riyadh, Sep-2026 - assumption pending the Contractor's substantiation
A27: 1.19 | B27: Site safety signage and notice boards | C27: No | D27: 12 | E27: 150 | F27: =D27*E27 -> 1800 | G27: HSE signage at the work area, distinct from the traffic signs at 1.20. Assessed market rate, Riyadh, Sep-2026 - assumption pending the Contractor's substantiation
A28: 1.20 | B28: Work-zone traffic signs up to 0.5 m2, supplied, installed, maintained and removed | C28: No | D28: 12 | E28: 1479.63 | F28: =D28*E28 -> 17755.56 | G28: Agreed rate under RFP-021 (assessment dated 30-Jun-2026), derived from RFP-002A, Sign World quotation 6512 - an agreed rate under Sub-Clause 13.3.4(a) of the Conditions of Contract
A29: 1.21 | B29: Concrete Jersey barriers - temporary hire for the works period, delivered, placed and removed | C29: Lm | D29: 100 | E29: 100 | F29: =D29*E29 -> 10000 | G29: Hire basis. The Bill of Quantities Part 9 rate (SAR 396/Lm) is for permanent supply and is not applied. 100 Lm assumed - to be confirmed against the work-area layout
A30: 1.22 | B30: Close-out at the tank site after demobilisation - completion inspection, correction list and warranties collation - site engineer | C30: day | D30: 3 | E30: 550 | F30: =D30*E30 -> 1650 | G30: 3 days after demobilisation: the Engineer's completion inspection, the correction list and the warranties collation. Reduced from 8 days because the site engineer's monthly period at 1.1 now runs to the end of demobilisation and the programmed close-out activity (QCD18TSEDMOB3020, 17 to 24-Dec-2026) falls inside it. Test records, ITP/WIR close-out and as-built drawings are in Item 7 (7.20 and 7.21), not here. Assessed market rate, Riyadh, Sep-2026 - assumption pending the Contractor's substantiation
A31: 1.23 | B31: Close-out at the tank site - document controller | C31: day | D31: 4 | E31: 500 | F31: =D31*E31 -> 2000 | G31: Assessed market rate, Riyadh, Sep-2026 - assumption pending the Contractor's substantiation
B32: TOTAL ITEM 1 - carried to 'Assessment'!J8 | F32: =SUM(F9:F31) -> 319680.56
A34: ITEM 2 - DESIGN AND ENGINEERING
A35: Tank structural design sits with the supplier (Stalwart technical offer SS-07-26-1516 dated 03-Aug-2026). All documentation is issued electronically via Aconex; no printing is included.
A36: Ref | B36: Description | C36: Unit | D36: Qty | E36: Rate (SAR) | F36: Amount (SAR) | G36: Basis
A37: 2.1 | B37: Design engineer - coordination, review of supplier calculations, method statements, ITPs | C37: month | D37: 2 | E37: 15000 | F37: =D37*E37 -> 30000 | G37: 2 months retained: the programme shows shop drawings 07 to 25-Aug-2026 (activities QCD18TSEENG1240 and 1250) with resubmissions to 29-Sep-2026 and the pipework shop drawings still in preparation, consistent with the period assessed. Assessed market rate, Riyadh, Sep-2026 - assumption pending the Contractor's substantiation
A38: 2.2 | B38: CAD draughtsman - shop drawings and design-stage submittals | C38: month | D38: 1.5 | E38: 8000 | F38: =D38*E38 -> 12000 | G38: 1.5 months retained on the same programme evidence as 2.1. As-built drawings at close-out are line 7.21. Assessed market rate, Riyadh, Sep-2026 - assumption pending the Contractor's substantiation
A39: 2.3 | B39: Dimensional and verticality survey of the erected tanks and as-built pick-up - 2-man crew with instrument | C39: crew-day | D39: 6 | E39: 1500 | F39: =D39*E39 -> 9000 | G39: Survey and levelling of the existing foundation (activity QCD18TSECONSL1050, 07 to 13-Sep-2026, cost-loaded by the Contractor at SAR 5,000.00) assessed at 3 crew-days for an existing base frame, plus a dimensional and verticality survey of each erected tank, 1.5 crew-days each (RFP Scope of Works, work package 3). Not setting out: the steel base frames are already installed on concrete supports (site photograph, Aug-2026). Assessed market rate, Riyadh, Sep-2026 - assumption pending the Contractor's substantiation
A40: 2.4 | B40: Submittal administration - document controller | C40: day | D40: 8 | E40: 500 | F40: =D40*E40 -> 4000 | G40: The programme carries 19 deliverable and submittal activities plus the material approval and inspection requests; 8 days of document control, doubled from the previous revision on that evidence. Assessed market rate, Riyadh, Sep-2026 - assumption pending the Contractor's substantiation
B41: TOTAL ITEM 2 - carried to 'Assessment'!J10 | F41: =SUM(F37:F40) -> 55000
A43: ITEM 3 - SAFE DISMANTLING OF DAMAGED TSE TANK-1
A44: The Contractor's lowest supplier quotation is adopted for dismantling, segregation and loading only. Haulage and handover of the materials are Item 4. The first-principles check below supports the amount; it is not carried to the assessment.
A45: Ref | B45: Description | C45: Unit | D45: Qty | E45: Rate (SAR) | F45: Amount (SAR) | G45: Basis
A46: 3.1 | B46: Adopted: Al Mousa Trading Co. quotation S04647 dated 10-Aug-2026 - existing tank dismantling, 1 No. | C46: item | D46: 1 | E46: 71000 | F46: =D46*E46 -> 71000 | G46: Lowest of three: PIPECO Q3363-R2 dated 06-Aug-2026 SAR 90,000; Professional Bayan PB/Q/0086/2026 dated 12-Aug-2026 SAR 80,000. Quotation validity has lapsed; written confirmation that it excludes haulage and disposal is outstanding.
B47: TOTAL ITEM 3 - carried to 'Assessment'!J12 | F47: =SUM(F46:F46) -> 71000
B48: First-principles check - information only, not carried to the assessment
A49: c.1 | B49: Dismantling crew, 6 No. x 12 working days | C49: man-day | D49: 72 | E49: 150 | F49: =D49*E49 -> 10800 | G49: Assessed market rate, Riyadh, Sep-2026 - assumption pending the Contractor's substantiation
A50: c.2 | B50: Rigger / charge hand, 1 No. x 12 working days | C50: man-day | D50: 12 | E50: 250 | F50: =D50*E50 -> 3000 | G50: Assessed market rate, Riyadh, Sep-2026 - assumption pending the Contractor's substantiation
A51: c.3 | B51: Mobile crane, 50 t | C51: day | D51: 12 | E51: 2500 | F51: =D51*E51 -> 30000 | G51: Assessed market rate, Riyadh, Sep-2026 - assumption pending the Contractor's substantiation
A52: c.4 | B52: Angle-grinder discs and abrasives | C52: No | D52: 200 | E52: 10 | F52: =D52*E52 -> 2000 | G52: Assessed market rate, Riyadh, Sep-2026 - assumption pending the Contractor's substantiation
A53: c.5 | B53: Oxy-fuel cutting set with gases | C53: set | D53: 1 | E53: 1500 | F53: =D53*E53 -> 1500 | G53: Assessed market rate, Riyadh, Sep-2026 - assumption pending the Contractor's substantiation
A54: c.6 | B54: Hand-tool wear and consumables | C54: tank | D54: 1 | E54: 1500 | F54: =D54*E54 -> 1500 | G54: Assessed market rate, Riyadh, Sep-2026 - assumption pending the Contractor's substantiation
A55: c.7 | B55: Pressure-washing unit for decontamination (RFP Scope of Works 4.2) | C55: day | D55: 3 | E55: 500 | F55: =D55*E55 -> 1500 | G55: Assessed market rate, Riyadh, Sep-2026 - assumption pending the Contractor's substantiation
A56: c.8 | B56: Wash water, tankered | C56: m3 | D56: 30 | E56: 10 | F56: =D56*E56 -> 300 | G56: Assessed market rate, Riyadh, Sep-2026 - assumption pending the Contractor's substantiation
A57: c.9 | B57: Decontamination labour, 2 No. x 3 days | C57: man-day | D57: 6 | E57: 150 | F57: =D57*E57 -> 900 | G57: Assessed market rate, Riyadh, Sep-2026 - assumption pending the Contractor's substantiation
A58: c.10 | B58: Residue collection and disposal drums | C58: No | D58: 8 | E58: 400 | F58: =D58*E58 -> 3200 | G58: Assessed market rate, Riyadh, Sep-2026 - assumption pending the Contractor's substantiation
A59: c.11 | B59: Decontamination records and supervision | C59: day | D59: 4 | E59: 500 | F59: =D59*E59 -> 2000 | G59: Assessed market rate, Riyadh, Sep-2026 - assumption pending the Contractor's substantiation
A60: c.12 | B60: Demolition method statement and risk assessment (RFP Scope of Works 4.1) | C60: day | D60: 3 | E60: 800 | F60: =D60*E60 -> 2400 | G60: Assessed market rate, Riyadh, Sep-2026 - assumption pending the Contractor's substantiation
... A62: c.14 | B62: Barricading and exclusion-zone controls | C62: item | D62: 1 | E62: 1000 | F62: =D62*E62 -> 1000 | G62: Assessed market rate, Riyadh, Sep-2026 - assumption pending the Contractor's substantiation
B63: Check total | F63: =SUM(F49:F62) -> 61700
A65: ITEM 4 - HAULAGE OF DISMANTLED MATERIALS
A66: The Engineer's (KEO) email of 30-Aug-2026: the dismantled materials are handed over to the Employer at a location assumed to be local. No disposal or tipping charge therefore applies. The Contractor's schedule priced this item as 14 loads x SAR 750 including tipping; the load count is retained, the rate is re-based to local haulage.
A67: Ref | B67: Description | C67: Unit | D67: Qty | E67: Rate (SAR) | F67: Amount (SAR) | G67: Basis
A68: 4.1 | B68: Haulage of dismantled materials to the Employer's local handover location | C68: load | D68: 14 | E68: 450 | F68: =D68*E68 -> 6300 | G68: 14 loads: bulked debris of one 34 m x 30 m x 4 m tank is about 150-250 m3 loose, i.e. 10-14 loads of a 30 m3 truck. Local haulage SAR 450/load - assumption, to be confirmed with the handover location
B69: TOTAL ITEM 4 - carried to 'Assessment'!J13 | F69: =SUM(F68:F68) -> 6300
A71: ITEM 5 - TEMPORARY WORKS, CONSTRUCTION EQUIPMENT AND SITE SUPPORT
A72: Covers what the tank supplier's offer (Stalwart technical offer SS-07-26-1516 dated 03-Aug-2026, with Al Mousa quotation S04488) requires the Contractor to provide free of cost: offloading and hoisting, scaffolding, storage and handling, power, and 4-6 helpers; plus general site support. On the recorded scope of that offer (not attached to this revision; to be confirmed against the original) Item 6 is supply and installation, so GRP erectors are not priced here. Boundary: Item 1 is management, welfare and mobilisation; Item 5 is execution plant, access, power and supplier attendance. Helper and plant days are assessed phase by phase on the 'Programme' tab, Section 4: one helper gang while only Tank 1 material is planned on site, a second gang only while the two erection fronts run together (22-Oct to 14-Nov-2026), walls and bracing as one front, attendance for the submitted durations, the Contractor's shorter Tank 2 durations shown as a sensitivity only. One boom truck and one telehandler are a provisional utilisation assumption pending the Contractor's plant schedule. Power: the works generator by day to completion of commissioning, the welfare generator continuously to the end of demobilisation. The Engineer's (KEO) email of 30-Aug-2026: suitable Site power is unlikely, so a generator is allowed; the Contractor's methodology uses forklifts, cranes and pallet jacks.
A73: Ref | B73: Description | C73: Unit | D73: Qty | E73: Rate (SAR) | F73: Amount (SAR) | G73: Basis
A74: 5.1 | B74: Boom truck (hiab) - offloading and erection support | C74: day | D74: =Programme!$G$126 -> 44 | E74: 1200 | F74: =D74*E74 -> 52800 | G74: Hire days from the 'Programme' tab, Section 4 (plant rows): offloading days plus the wall, bracing, roof-support and roof lifting days of both tanks, one unit serving concurrent activities. The Contractor's methodology names forklifts, cranes and pallet jacks (Engineer's (KEO) email of 30-Aug-2026); no plant schedule has been submitted. Assessed market rate, Riyadh, Sep-2026 - assumption pending the Contractor's substantiation
A75: 5.2 | B75: Telehandler / forklift | C75: day | D75: =Programme!$G$128 -> 62 | E75: 900 | F75: =D75*E75 -> 55800 | G75: Hire days from the 'Programme' tab, Section 4: offloading, base, wall and roof panel days of both tanks, one unit serving concurrent activities - a provisional utilisation assumption. Assessed market rate, Riyadh, Sep-2026 - assumption pending the Contractor's substantiation
A76: 5.3 | B76: Perimeter scaffolding and edge protection - supply, erect, 3-month hire, dismantle | C76: m2 | D76: 1024 | E76: 55 | F76: =D76*E76 -> 56320 | G76: 2 tanks x 128 m perimeter x 4.0 m height; the rate includes a 3-month hire, which covers the access window D6 on the 'Programme' tab, Section 3 on either basis. Assessed market rate, Riyadh, Sep-2026 - assumption pending the Contractor's substantiation
A77: 5.4 | B77: Mobile aluminium access towers, 2 No. for the access window, whole hire months | C77: tower-month | D77: =Programme!$G$129 -> 4 | E77: 1800 | F77: =D77*E77 -> 7200 | G77: 2 No. for the access window D6 on the 'Programme' tab, Section 3, rounded up to whole hire months. Assessed market rate, Riyadh, Sep-2026 - assumption pending the Contractor's substantiation
A78: 5.5 | B78: Access-tower relocations and re-inspections | C78: No | D78: 4 | E78: 400 | F78: =D78*E78 -> 1600 | G78: Assessed market rate, Riyadh, Sep-2026 - assumption pending the Contractor's substantiation
A79: 5.6 | B79: Podium steps, 2 No. for the access window, whole hire months | C79: unit-month | D79: =Programme!$G$130 -> 4 | E79: 350 | F79: =D79*E79 -> 1400 | G79: As 5.4. Assessed market rate, Riyadh, Sep-2026 - assumption pending the Contractor's substantiation
A80: 5.7 | B80: Generator 100 kVA for the works, daytime running with fuel | C80: month | D80: =Programme!$G$131 -> 3.8 | E80: 11000 | F80: =D80*E80 -> 41800 | G80: Works period D2 on the 'Programme' tab, Section 3, to completion of commissioning. Power is excluded by both tank suppliers; no Site power expected at the tank site. Assessed market rate, Riyadh, Sep-2026 - assumption pending the Contractor's substantiation
A81: 5.8 | B81: Generator 30 kVA for the site office and welfare cabins, continuous running with fuel, whole period | C81: month | D81: =Programme!$G$132 -> 4.1 | E81: 6000 | F81: =D81*E81 -> 24600 | G81: Site period D1 on the 'Programme' tab, Section 3; air conditioning and lighting run around the clock at a separate site. Assessed market rate, Riyadh, Sep-2026 - assumption pending the Contractor's substantiation
A82: 5.9 | B82: Site transport, pick-up / flatbed | C82: month | D82: =Programme!$G$133 -> 4.1 | E82: 3000 | F82: =D82*E82 -> 12300 | G82: Site period D1 on the 'Programme' tab, Section 3. Assessed market rate, Riyadh, Sep-2026 - assumption pending the Contractor's substantiation
A83: 5.10 | B83: Contractor's helpers - attendance to the tank supplier, offloading and panel handling, man-months from the resource matrix | C83: man-month | D83: =Programme!$G$134 -> 18.5 | E83: 3000 | F83: =D83*E83 -> 55500 | G83: Supplier condition: 4-6 non-skilled labourers for material handling (recorded scope). Helper-days on the 'Programme' tab, Section 4: one gang of 5 attending the single front for the submitted durations, a second gang only while two fronts run, offloading before a front opens, mobilisation and dismantling attendance; converted at 26 working days a month. The Contractor's histogram helper row (85 man-weeks) is reconciled week by week there; it is not adopted. Assessed market rate, Riyadh, Sep-2026 - assumption pending the Contractor's substantiation
A84: 5.11 | B84: Power-tool hire | C84: month | D84: =Programme!$G$135 -> 2.7 | E84: 2500 | F84: =D84*E84 -> 6750 | G84: Erection window D3 on the 'Programme' tab, Section 3. Assessed market rate, Riyadh, Sep-2026 - assumption pending the Contractor's substantiation
A85: 5.12 | B85: Sealant-application tools and jointing consumables | C85: tank | D85: 0 | E85: 1500 | F85: =D85*E85 -> 0 | G85: Provisionally not assessed, to avoid duplication: sealant application at every joint is the erection work of RFP Scope of Works work package 2, performed by the supplier under Item 6 on the recorded scope of its offer, whose conditions ask the Contractor for offloading, scaffolding, storage, power and helpers only. To be confirmed against the original offer. Previously 2 tanks at SAR 1,500.00
A86: 5.13 | B86: Fixings, touch-up and miscellaneous consumables | C86: tank | D86: 0 | E86: 2250 | F86: =D86*E86 -> 0 | G86: Provisionally not assessed, to avoid duplication: bolts, nuts, washers and tie rods are supplied and fixed by the tank supplier (Item 6, recorded scope); no Contractor fixing or touch-up work is identified. To be confirmed against the original offer. Previously 2 tanks at SAR 2,250.00
A87: 5.14 | B87: Mobile lighting towers, 2 No. for the erection window | C87: unit-month | D87: =Programme!$G$136 -> 5.4 | E87: 1200 | F87: =D87*E87 -> 6480 | G87: 2 No. for the erection window D3 on the 'Programme' tab, Section 3. Assessed market rate, Riyadh, Sep-2026 - assumption pending the Contractor's substantiation
A88: 5.15 | B88: Temporary distribution boards and cabling | C88: set | D88: 2 | E88: 1400 | F88: =D88*E88 -> 2800 | G88: Assessed market rate, Riyadh, Sep-2026 - assumption pending the Contractor's substantiation
B89: TOTAL ITEM 5 - carried to 'Assessment'!J14 | F89: =SUM(F74:F88) -> 325350
A91: ITEM 6 - GRP SECTIONAL TANKS 4,080 m3 - SUPPLY AND INSTALLATION, 2 No.
A92: The Contractor's adopted lowest quotation is taken at net supplier cost; the 5 per cent Overhead and Profit is applied once on the 'Assessment' tab. The quotation is for an insulated tank. The Engineer's (KEO) email of 30-Aug-2026: thermal insulation is not required, so a lower non-insulated price is expected and has been requested. The rate below will change when it is received.
A93: Ref | B93: Description | C93: Unit | D93: Qty | E93: Rate (SAR) | F93: Amount (SAR) | G93: Basis
A94: 6.1 | B94: Adopted: Al Mousa Trading Co. quotation S04488 dated 09-Jul-2026 with Stalwart technical offer SS-07-26-1516 dated 03-Aug-2026 - sectional GRP tank 34 m x 30 m x 4.0 m, supplied and installed, rate per tank | C94: No | D94: 1 | E94: 2763500 | F94: =D94*E94 -> 2763500 | G94: Lowest of three: PIPECO Q3363-R2 dated 06-Aug-2026 SAR 2,899,000/tank (insulated, 1 partition, 10-year warranty on manufacture and installation); Professional Bayan PB/Q/0086/2026 dated 12-Aug-2026 SAR 2,950,000/tank (ex-works supply only). Rate per gross m3: SAR 677 against PIPECO SAR 711. Quotation lapsed 08-Aug-2026; whether bottom/base panels are included is not confirmed.
B95: RATE PER TANK - carried to 'Assessment'!J16 (x 2 No.) | F95: =SUM(F94:F94) -> 2763500
A97: ITEM 7 - TESTING, COMMISSIONING AND HANDOVER, BOTH TANKS
A98: The Engineer's (KEO) email of 30-Aug-2026: installation and testing will not be in parallel; one tank is filled and the water is re-used for the second by pumping across. This basis is carried. The Contractor's programme tests both tanks in parallel on 09 to 16-Dec-2026, which would need 7,548 m3 of water at once; that basis is shown beside this one on the 'Programme' tab, Section 4 (lines 7.1 to 7.5 and 7.22) and is not carried. The sequential test is fitted to the submitted dates ('Programme' tab, P18 to P22): Tank 1 is tested before the tie-in, within its programme float, on the conditional assumption of an Engineer-approved method with the water retained in Tank 1; the water is transferred once Tank 1 has passed and Tank 2 is ready; component checks follow the tie-in; integrated commissioning follows the last of the tie-in, the Tank 2 test and the component checks. Each test is 7 elapsed working days (fill or transfer, hold, inspection); the attendance priced is set out line by line. The Contractor arranges the water; the source is being checked by the Employer, so tankered supply is assumed. Excludes the leak-test supervision already in the supplier's price (Item 6) and any re-testing after an unsatisfactory test, which is the Contractor's obligation under RFP Scope of Works 5.1. External pipework testing is Item 8. Scope: RFP Scope of Works 5.1 to 5.3.
A99: Ref | B99: Description | C99: Unit | D99: Qty | E99: Rate (SAR) | F99: Amount (SAR) | G99: Basis
A100: 7.1 | B100: Test water - first tank fill to test level | C100: m3 | D100: =Programme!$G$137 -> 3774 | E100: 6 | F100: =D100*E100 -> 22644 | G100: 3,774 m3 effective at 3.7 m water level (RFP Scope of Works section 1); one fill, the water re-used for Tank 2. Tankered at SAR 6.00/m3 - assumption; falls away if a network fill is confirmed
A101: 7.2 | B101: Transfer pump hire - Tank 1 to Tank 2 | C101: day | D101: =Programme!$G$138 -> 7 | E101: 500 | F101: =D101*E101 -> 3500 | G101: The transfer P19 and the Tank 2 test P20 on the 'Programme' tab (7 days); pump duty an assessed assumption pending the Contractor's method statement. Assessed market rate, Riyadh, Sep-2026 - assumption pending the Contractor's substantiation
A102: 7.3 | B102: Transfer hoses and fittings hire | C102: week | D102: =Programme!$G$139 -> 1 | E102: 1000 | F102: =D102*E102 -> 1000 | G102: Assessed market rate, Riyadh, Sep-2026 - assumption pending the Contractor's substantiation
A103: 7.4 | B103: Transfer labour, 2 No. x 3 days | C103: man-day | D103: =Programme!$G$140 -> 6 | E103: 150 | F103: =D103*E103 -> 900 | G103: 2 No. x 3 days, the transfer window P19 on the 'Programme' tab. Assessed market rate, Riyadh, Sep-2026 - assumption pending the Contractor's substantiation
A104: 7.5 | B104: Top-up water for losses and test level | C104: m3 | D104: =Programme!$G$141 -> 377 | E104: 6 | F104: =D104*E104 -> 2262 | G104: 10 per cent of one fill, covering losses while the water is retained in Tank 1 between its test and the transfer to Tank 2 - assumption
A105: 7.6 | B105: Disinfection chemicals, hypochlorite (AWWA C652) | C105: kg | D105: 800 | E105: 6 | F105: =D105*E105 -> 4800 | G105: Assessed market rate, Riyadh, Sep-2026 - assumption pending the Contractor's substantiation
A106: 7.7 | B106: Chlorine dosing equipment hire | C106: week | D106: 2 | E106: 750 | F106: =D106*E106 -> 1500 | G106: Assessed market rate, Riyadh, Sep-2026 - assumption pending the Contractor's substantiation
A107: 7.8 | B107: Disinfection and flushing labour, 2 No. x 10 days | C107: man-day | D107: 20 | E107: 150 | F107: =D107*E107 -> 3000 | G107: Assessed market rate, Riyadh, Sep-2026 - assumption pending the Contractor's substantiation
A108: 7.9 | B108: Dechlorination chemicals for discharge | C108: kg | D108: 400 | E108: 5 | F108: =D108*E108 -> 2000 | G108: Assessed market rate, Riyadh, Sep-2026 - assumption pending the Contractor's substantiation
...

Sheet Build-Up Comparison
A1: CONTRACTOR'S BUILD-UP COMPARED WITH THE ASSESSMENT
A2: TSE Irrigation Storage Tanks and Associated Pipeworks (RFP-027) - Contract QPMO-410-CT-05958
A3: Contractor: SAMA Construction | Engineer: KEO | Cost Consultant: WT Partnership | Rev 02, 30-Sep-2026
A4: The Contractor was asked on 25-Aug-2026 to substantiate the lump-sum items in its proposal. It submitted a rate build-up for Items 1, 5, 7 and 8. This tab sets each component of that submission against the assessed build-up on the 'Build-Up' tab and records whether the amount claimed is supported. Column F sets against each of the Contractor's components the 'Build-Up' lines assessed for the same work, so that the two build-ups can be read side by side and both columns foot to the item totals. All amounts exclude VAT.
A6: 1. SUMMARY
A7: Item | B7: Description | E7: Claimed by the Contractor (SAR) | F7: Assessed (SAR) | G7: Difference (SAR) | H7: Conclusion
A8: 1 | B8: Site mobilisation, temporary facilities and welfare | E8: =Assessment!$F$8 -> 680000 | F8: =Assessment!$K$8 -> 319680.56 | G8: =E8-F8 -> 360319.44 | H8: Not substantiated. A separate site establishment is allowable and is assessed in Section 3 of this tab.
A9: 5 | B9: Temporary works, construction equipment and site support | E9: =Assessment!$F$14 -> 504192.02 | F9: =Assessment!$K$14 -> 325350 | G9: =E9-F9 -> 178842.02 | H9: Not substantiated. No plant numbers, periods or rates; includes a contingency line. See Section 4 of this tab.
A10: 7 | B10: Testing, commissioning and handover | E10: =Assessment!$F$17 -> 426400 | F10: =Assessment!$K$17 -> 102306 | G10: =E10-F10 -> 324094 | H10: Not substantiated. No volumes, counts or rates; includes re-testing. See Section 5 of this tab.
A11: 8 | B11: Piping, instrumentation, supports and accessories | E11: =Assessment!$F$18 -> 420000 | F11: =Assessment!$K$18 -> 245200 | G11: =E11-F11 -> 174800 | H11: Not substantiated. No quantities; take-off outstanding. See Section 6 of this tab.
B12: Total of the four items submitted | E12: =SUM(E8:E11) -> 2030592 | F12: =SUM(F8:F11) -> 992536.56 | G12: =E12-F12 -> 1038055.5 | H12: The submission does not change the assessment.
A13: Items 2 (Design and engineering, SAR 85,000.00) and 4 (Removal and disposal, SAR 10,500.00) were also requested and have not been submitted.
A15: 2. HOW THE CONTRACTOR'S BUILD-UP IS CONSTRUCTED
A16: - Each amount is the claimed lump sum multiplied by an assumed percentage, for example 25 per cent x SAR 504,192.02. The percentages are set to total 100 per cent, so each sheet returns the figure it started from.
A17: - No quantities and no unit rates are stated in any of the four sheets.
A18: - Plant is named without capacity, number, hire period or rate. Labour is given as ranges such as "approx. 4-6 crew", not as man-days.
A19: - The Item 1 percentages are a weighting of 83 parts (20, 6, 8, 12, 8, 7, 10 and 12), which is why they carry six decimal places.
A20: - The submission allocates the sums already claimed; it does not build them up, and it does not allow the quantities and rates to be substantiated as Sub-Clause 12.3.2 of the Conditions of Contract requires.
A22: 3. ITEM 1 - SITE MOBILISATION, TEMPORARY FACILITIES AND WELFARE
A23: The tank site is in the lower plateau, outside the D-18 site boundary, so a separate site establishment is allowable. The Contractor's components are the Contract Preliminaries headings restated with percentages; none is built up as quantity x rate.
A24: Ref | B24: Component as submitted by the Contractor | C24: Basis stated by the Contractor | D24: % of item | E24: Amount claimed (SAR) | F24: Assessed (SAR) | G24: Difference (SAR) | H24: Assessment comment
A25: 1.1 | B25: Heavy equipment mobilization/demobilization (cranes, trucks, machinery transport to/from site) | C25: Site establishment cost driver for the scale of works | D25: 0.240964 | E25: 163855.52 | F25: ='Build-Up'!$F$22 -> 6250 | G25: =E25-F25 -> 157605.52 | H25: Assessed as mobilisation trips for cabins, containers and small plant ('Build-Up' 1.14); demobilisation is assessed against the Contractor's line 1.8 in this table. No trips or rates stated. The tank installer's own mobilisation is within the supplier quotation adopted under Item 6 (Al Mousa S04488 dated 09-Jul-2026).
A26: 1.2 | B26: Construction Facilities - welfare & First Aid facilities | C26: Per Contract Preliminaries: welfare and First Aid facilities provision at site | D26: 0.072289 | E26: 49156.52 | F26: ='Build-Up'!$F$14+'Build-Up'!$F$15+'Build-Up'!$F$16 -> 23370 | G26: =E26-F26 -> 25786.52 | H26: Assessed as a site office cabin, a welfare cabin and a WC unit for 3 months ('Build-Up' 1.6 to 1.8). No units, period or rate stated.
A27: 1.3 | B27: Vehicular Access & Parking (traffic signs, safety barriers, etc.) | C27: Per Contract: Vehicular Access and Parking, including traffic signs, safety barriers, etc. | D27: 0.096386 | E27: 65542.48 | F27: ='Build-Up'!$F$28+'Build-Up'!$F$29 -> 27755.56 | G27: =E27-F27 -> 37786.92 | H27: Assessed as 12 traffic signs at the RFP-021 agreed rate and 100 Lm of hired barriers ('Build-Up' 1.20 and 1.21). No quantities stated.
A28: 1.4 | B28: Personnel mobilization (transport, camp/accommodation setup, induction) | C28: Personnel mobilization to site | D28: 0.144578 | E28: 98313.04 | F28: ='Build-Up'!$F$20 -> 16400 | G28: =E28-F28 -> 81913.04 | H28: Assessed as daily workforce transport to the tank site ('Build-Up' 1.12). Camp and accommodation set-up is not allowed: the workforce is already employed and accommodated under the Contract.
A29: 1.5 | B29: Temporary utilities connection (power distribution, water supply to site) | C29: Standard site establishment item | D29: 0.096386 | E29: 65542.48 | F29: ='Build-Up'!$F$17+'Build-Up'!$F$18 -> 14035 | G29: =E29-F29 -> 51507.48 | H29: Assessed as tankered site water and a storage tank for the whole period ('Build-Up' 1.9 and 1.10). Power is assessed against the Contractor's Item 5, line 5.4 (generators), in Section 4 of this tab, and is not repeated here. No basis stated.
A30: 1.6 | B30: Permits, insurance, HSE setup & signage | C30: Standard preliminary cost | D30: 0.084337 | E30: 57349.16 | F30: ='Build-Up'!$F$10+'Build-Up'!$F$25+'Build-Up'!$F$26+'Build-Up'!$F$27 -> 62800 | G30: =E30-F30 -> -5450.84 | H30: Assessed as a dedicated HSE officer, an insurance endorsement extending the Contract cover to the tank site, PPE and site safety signage ('Build-Up' 1.2 and 1.17 to 1.19). Traffic signs are against line 1.3. No basis stated.
A31: 1.7 | B31: Close out (Completion and Correction List, Warranties, Project Record Documents) | C31: Per Contract Preliminaries Item 22: Close out documentation | D31: 0.120482 | E31: 81927.76 | F31: ='Build-Up'!$F$30+'Build-Up'!$F$31 -> 3650 | G31: =E31-F31 -> 78277.76 | H31: Assessed as a separate completion procedure for the tank site: inspections, correction list and warranties ('Build-Up' 1.22 and 1.23). Test records, ITP/WIR close-out and as-built drawings are assessed under Item 7 and not repeated. No resource or duration stated.
A32: 1.8 | B32: Demobilization at completion (equipment removal, site clean-up, facility removal) | C32: Mirrors mobilization scope at close-out | D32: 0.144578 | E32: 98313.04 | F32: ='Build-Up'!$F$23+'Build-Up'!$F$24 -> 8050 | G32: =E32-F32 -> 90263.04 | H32: Assessed as demobilisation trips and site clean-up ('Build-Up' 1.15 and 1.16). No trips, labour or rates stated.
B33: Assessed but not identified in the Contractor's build-up: site supervision, storage and security | E33: 0 | F33: ='Build-Up'!$F$9+'Build-Up'!$F$11+'Build-Up'!$F$12+'Build-Up'!$F$13+'Build-Up'!$F$19+'Build-Up'!$F$21 -> 157370 | G33: =E33-F33 -> -157370 | H33: Site engineer, QA/QC inspector, works foreman, storekeeper, storage containers and watchman ('Build-Up' 1.1, 1.3 to 1.5, 1.11 and 1.13). The Contractor's manpower schedule places site staff in general overheads and prices none here.
B34: Totals for this item | E34: =SUM(E25:E33) -> 680000 | F34: =SUM(F25:F33) -> 319680.56 | G34: =E34-F34 -> 360319.44 | H34: Column F foots to the item total on the 'Assessment' tab, row 8.
A35: The manpower schedule submitted with Item 1 states that the full-time roles' 151-day cost and the part-time allocations are carried under the Contractor's general overheads and preliminaries, and that it "does not reprice Item 1's Est. % / Est. Amount values". It provides no support for the amount claimed. The 151-day duration is asserted without a programme.
A37: 4. ITEM 5 - TEMPORARY WORKS, CONSTRUCTION EQUIPMENT AND SITE SUPPORT
A38: The stated basis for six of the eight lines is a quotation of the RFP item description. Restating the description does not substantiate the price.
A39: Ref | B39: Component as submitted by the Contractor | C39: Basis stated by the Contractor | D39: % of item | E39: Amount claimed (SAR) | F39: Assessed (SAR) | G39: Difference (SAR) | H39: Assessment comment
A40: 5.1 | B40: Scaffolding & access platforms (for tank erection/bracing works) | C40: Per RFP wording: 'Scaffolding' | D40: 0.15 | E40: 75628.803 | F40: ='Build-Up'!$F$76+'Build-Up'!$F$77+'Build-Up'!$F$78+'Build-Up'!$F$79 -> 66520 | G40: =E40-F40 -> 9108.803 | H40: Assessed as 1,024 m2 of perimeter scaffold, access towers and podium steps ('Build-Up' 5.3 to 5.6). No area, period or rate stated.
A41: 5.2 | B41: Mobile crane(s) rental for tank panel erection (duration-based) | C41: Per RFP wording: 'cranes' | D41: 0.25 | E41: 126048.01 | F41: ='Build-Up'!$F$75 -> 55800 | G41: =E41-F41 -> 70248.005 | H41: Assessed as a telehandler for the hire days on the 'Programme' tab, Section 4 ('Build-Up' 5.2): the existing base frames and 4 m panel height do not call for a mobile crane. The Contractor's plant schedule is awaited. No capacity, units, period or rate stated.
A42: 5.3 | B42: Boom trucks / man-lifts for elevated works | C42: Per RFP wording: 'boom trucks' | D42: 0.12 | E42: 60503.042 | F42: ='Build-Up'!$F$74 -> 52800 | G42: =E42-F42 -> 7703.0424 | H42: Assessed as a boom truck for the hire days on the 'Programme' tab, Section 4 ('Build-Up' 5.1). No units, period or rate stated.
A43: 5.4 | B43: Generators - rental & fuel for site power | C43: Per RFP wording: 'generators' | D43: 0.1 | E43: 50419.202 | F43: ='Build-Up'!$F$80+'Build-Up'!$F$81+'Build-Up'!$F$88 -> 69200 | G43: =E43-F43 -> -18780.798 | H43: Assessed as a 100 kVA works set by day and a 30 kVA welfare set running continuously, both for the whole period with fuel, and distribution boards ('Build-Up' 5.7, 5.8 and 5.15). All site power is assessed here; none is assessed under the Contractor's Item 1, line 1.5 (temporary utilities), in Section 3 of this tab, so there is no double count. No set size, period or fuel basis stated.
A44: 5.5 | B44: Site trucks & transport (materials, spoil, deliveries) | C44: Per RFP wording: 'trucks' | D44: 0.1 | E44: 50419.202 | F44: ='Build-Up'!$F$82 -> 12300 | G44: =E44-F44 -> 38119.202 | H44: Assessed as a site pick-up for 3 months ('Build-Up' 5.9). No vehicles, period or rate stated.
A45: 5.6 | B45: Small tools & consumables (hand tools, torque tools, sealants application tools) | C45: Per RFP wording: 'small tools' | D45: 0.08 | E45: 40335.362 | F45: ='Build-Up'!$F$84+'Build-Up'!$F$85+'Build-Up'!$F$86 -> 6750 | G45: =E45-F45 -> 33585.362 | H45: Assessed as power-tool hire, jointing and general consumables ('Build-Up' 5.11 to 5.13). No basis stated.
A46: 5.7 | B46: Temporary facilities upkeep (site cabins, storage, lighting) for works duration | C46: Per RFP wording: 'temporary facilities' | D46: 0.12 | E46: 60503.042 | F46: ='Build-Up'!$F$87 -> 6480 | G46: =E46-F46 -> 54023.042 | H46: Assessed as lighting towers ('Build-Up' 5.14); cabins and storage are under Item 1. No units, period or rate stated.
A47: 5.8 | B47: Other equipment/resources (contingency for unlisted items) | C47: Per RFP wording: 'other equipment/resources' | D47: 0.08 | E47: 40335.362 | F47: 0 | G47: =E47-F47 -> 40335.362 | H47: Not allowed. A contingency for unidentified items is not a cost.
B48: Assessed but not identified in the Contractor's build-up: attendance labour for the tank supplier | E48: 0 | F48: ='Build-Up'!$F$83 -> 55500 | G48: =E48-F48 -> -55500 | H48: Helper-days assessed phase by phase on the 'Programme' tab, Section 4, converted to man-months ('Build-Up' 5.10).
B49: Totals for this item | E49: =SUM(E40:E48) -> 504192.02 | F49: =SUM(F40:F48) -> 325350 | G49: =E49-F49 -> 178842.02 | H49: Column F foots to the item total on the 'Assessment' tab, row 14.
A51: 5. ITEM 7 - TESTING, COMMISSIONING AND HANDOVER
A52: Claimed as 2 No. at SAR 213,200.00 each. The basic leak-test supervision is already in the tank supplier's price under Item 6. Assessed amounts are for both tanks. 'Scope' in the Contractor's stated basis means the RFP Scope of Works.
A53: Ref | B53: Component as submitted by the Contractor | C53: Basis stated by the Contractor | D53: % of item | E53: Amount claimed (SAR) | F53: Assessed (SAR) | G53: Difference (SAR) | H53: Assessment comment
A54: 7.1 | B54: Hydrostatic / leak test per tank (water fill, 24-hr hold, drain, re-test if needed) | C54: Per Scope 5.1 | D54: 0.3 | E54: 127920 | F54: ='Build-Up'!$F$100+'Build-Up'!$F$101+'Build-Up'!$F$102+'Build-Up'!$F$103+'Build-Up'!$F$104+'Build-Up'!$F$105+'Build-Up'!$F$106+'Build-Up'!$F$107+'Build-Up'!$F$108+'Build-Up'!$F$109+'Build-Up'!$F$110+'Build-Up'!$F$111+'Build-Up'!$F$121 -> 54506 | G54: =E54-F54 -> 73414 | H54: Assessed as one fill with transfer to the second tank, disinfection, flushing, water-quality testing and standby ('Build-Up' 7.1 to 7.12 and 7.22). Re-testing is the Contractor's obligation and is not allowed. No volume, source or rate stated.
A55: 7.2 | B55: Component & instrumentation function testing (level instruments, valves, nozzles) | C55: Per Scope 5.2 - T&C Programme | D55: 0.2 | E55: 85280 | F55: ='Build-Up'!$F$114+'Build-Up'!$F$116+'Build-Up'!$F$117+'Build-Up'!$F$118 -> 12000 | G55: =E55-F55 -> 73280 | H55: Assessed as an electrician, a calibration technician, certified calibrations and test equipment ('Build-Up' 7.15 and 7.17 to 7.19). No counts or rates stated.
A56: 7.3 | B56: Subsystem validation (tank-pump-network interface verification) | C56: Per Scope 5.2 | D56: 0.15 | E56: 63960 | F56: ='Build-Up'!$F$113+'Build-Up'!$F$115 -> 9800 | G56: =E56-F56 -> 54160 | H56: Assessed as MEP technicians and integration coordination ('Build-Up' 7.14 and 7.16). No resource or duration stated.
A57: 7.4 | B57: Integrated system commissioning (full operational demonstration, witness testing) | C57: Per Scope 5.2 | D57: 0.2 | E57: 85280 | F57: ='Build-Up'!$F$112 -> 16000 | G57: =E57-F57 -> 69280 | H57: Assessed as a commissioning engineer for 15 days ('Build-Up' 7.13). The Engineer's representative attendance, included in the Contractor's labour, is not a Contractor cost.
A58: 7.5 | B58: Documentation & handover (as-built, test certificates, O&M manuals, ITP/WIR close-out) | C58: Per Scope 5.3 | D58: 0.15 | E58: 63960 | F58: ='Build-Up'!$F$119+'Build-Up'!$F$120 -> 10000 | G58: =E58-F58 -> 53960 | H58: Assessed as a technical clerk and as-built mark-ups ('Build-Up' 7.20 and 7.21). No resource or duration stated.
B59: Totals for this item | E59: =SUM(E54:E58) -> 426400 | F59: =SUM(F54:F58) -> 102306 | G59: =E59-F59 -> 324094 | H59: Column F foots to the item total on the 'Assessment' tab, row 17.
A61: 6. ITEM 8 - PIPING, INSTRUMENTATION, SUPPORTS AND ACCESSORIES
A62: Material supply (lines 8.1 to 8.3) is 60 per cent of the claim, SAR 252,000.00, stated without a single length, diameter or count. The take-off from the marked-up schematic in the RFP was requested and has not been provided. The assessed rates are supplied and installed, so the Contractor's separate labour line is compared against the tie-in work only. 'Scope' in the Contractor's stated basis means the RFP Scope of Works.
A63: Ref | B63: Component as submitted by the Contractor | C63: Basis stated by the Contractor | D63: % of item | E63: Amount claimed (SAR) | F63: Assessed (SAR) | G63: Difference (SAR) | H63: Assessment comment
A64: 8.1 | B64: Pipe material supply (uPVC Sch.40 <DN150 / GRP or DI >DN150) | C64: Per Scope 3.1 General Piping Requirements | D64: 0.3 | E64: 126000 | F64: ='Build-Up'!$F$129+'Build-Up'!$F$130+'Build-Up'!$F$132+'Build-Up'!$F$133+'Build-Up'!$F$134 -> 107200 | G64: =E64-F64 -> 18800 | H64: Assessed as 200 m of DN200-300 and 60 m of small-bore pipework with joints and flanges, supplied and installed ('Build-Up' 8.1, 8.2 and 8.4 to 8.6). No lengths or diameters stated; take-off awaited.
A65: 8.2 | B65: Valves supply (resilient-seated butterfly, lever or gearbox operated per size) | C65: Per Scope 3.1 | D65: 0.18 | E65: 75600 | F65: ='Build-Up'!$F$131 -> 55000 | G65: =E65-F65 -> 20600 | H65: Assessed as 10 valves DN150-300, installed ('Build-Up' 8.3). No sizes or numbers stated.
A66: 8.3 | B66: Pipe supports, brackets & anchor clamps (galvanized/316SS) | C66: Per Scope 3.1 | D66: 0.12 | E66: 50400 | F66: ='Build-Up'!$F$135+'Build-Up'!$F$136 -> 15000 | G66: =E66-F66 -> 35400 | H66: Assessed as 40 supports and 8 thrust blocks ('Build-Up' 8.7 and 8.8). No numbers stated.
A67: 8.4 | B67: Fabrication & installation labor (fitting, jointing, tie-ins to network) | C67: Standard piping installation cost driver | D67: 0.2 | E67: 84000 | F67: ='Build-Up'!$F$142+'Build-Up'!$F$143 -> 20000 | G67: =E67-F67 -> 64000 | H67: Assessed as the two network tie-ins with coordination ('Build-Up' 8.14 and 8.15); installation of pipework, valves and supports is within the supplied-and-installed rates above. Crew range only stated.
A68: 8.5 | B68: Instrumentation connections & testing (pressure gauge tap, sample tap, 1.5x pressure test, hydrostatic test & records) | C68: Per General Piping Requirements | D68: 0.15 | E68: 63000 | F68: ='Build-Up'!$F$137+'Build-Up'!$F$138+'Build-Up'!$F$139+'Build-Up'!$F$140+'Build-Up'!$F$141+'Build-Up'!$F$144+'Build-Up'!$F$145+'Build-Up'!$F$146+'Build-Up'!$F$147 -> 40000 | G68: =E68-F68 -> 23000 | H68: Assessed as level instrumentation, gauges, sample taps and pipework testing ('Build-Up' 8.9 to 8.13 and 8.16 to 8.19). No counts stated.
A69: 8.6 | B69: Colour-coding, identification tagging & flow direction marking | C69: Per Scope 3.1 | D69: 0.05 | E69: 21000 | F69: ='Build-Up'!$F$148+'Build-Up'!$F$149 -> 8000 | G69: =E69-F69 -> 13000 | H69: Assessed as 260 m of colour banding and 70 tags ('Build-Up' 8.20 and 8.21). No lengths or counts stated.
B70: Totals for this item | E70: =SUM(E64:E69) -> 420000 | F70: =SUM(F64:F69) -> 245200 | G70: =E70-F70 -> 174800 | H70: Column F foots to the item total on the 'Assessment' tab, row 18.
A72: 7. INFORMATION REQUESTED FROM THE CONTRACTOR AND STILL OUTSTANDING
A73: The substantiation request was issued by WT Partnership to the Contractor via Aconex on 25-Aug-2026 under Sub-Clauses 13.3.1 and 12.3.2 of the Conditions of Contract. A follow-up clarification request was prepared after the Engineer's (KEO) email of 30-Aug-2026; its issue is to be confirmed before it is relied on.
A74: No. | B74: Requested | C74: Requested in | H74: Status at 30-Sep-2026
A75: 1 | B75: Detailed build-ups for Items 2 and 4 | C75: WT Partnership Aconex substantiation request dated 25-Aug-2026 | H75: Not submitted
A76: 2 | B76: Revalidated supplier quotations; both had lapsed before the proposal was submitted | C76: WT Partnership Aconex substantiation request dated 25-Aug-2026; WT Partnership follow-up clarification request (issue to be confirmed). | H76: Not received
A77: 3 | B77: Written confirmation whether bottom/base panels are included in the tank price | C77: WT Partnership Aconex substantiation request dated 25-Aug-2026; WT Partnership follow-up clarification request (issue to be confirmed). | H77: Not received
A78: 4 | B78: Execution programme and the impact on the Key Dates and Time for Completion | C78: WT Partnership Aconex substantiation request dated 25-Aug-2026; WT Partnership follow-up clarification request (issue to be confirmed). | H78: Baseline programme (data date 01-Jul-2026), S-curve, cash flow, manpower histogram and look-ahead received 29-Sep-2026; under the Engineer's approval. The impact on the Key Dates and Time for Completion is not stated
A79: 5 | B79: Revised quotations from all three suppliers priced on a non-insulated basis | C79: This assessment. | H79: Not submitted
A80: 6 | B80: Basis of Item 7 reflecting re-use of test water from the first tank to the second | C80: This assessment. | H80: Not addressed
A81: 7 | B81: Basis of Item 4 reflecting handover of dismantled materials to the Employer | C81: This assessment. | H81: Not addressed
A82: 8 | B82: Quantity take-off for Item 8 from the marked-up schematic forming part of the RFP | C82: This assessment. | H82: Not submitted
A83: 9 | B83: Plant schedule showing type, number, duration and utilisation | C83: This assessment. | H83: Not submitted; the programme is cost-loaded but carries no plant resources
A84: 10 | B84: Whose labour the direct manpower histogram (221 man-weeks, 28-Aug to 11-Dec-2026) represents: whether the tank supplier's erection crews, priced within Item 6, are included | C84: This assessment. | H84: Not yet requested
A85: 11 | B85: Quantity take-off for Item 8 from the pipework shop drawings once approved (returned Code C; resubmission 28 to 30-Sep-2026 per the look-ahead) | C85: This assessment. | H85: Not yet requested
A86: 12 | B86: Material approval requests for the HDPE main-line pipe, the gate valve DN300 and the motorised butterfly valve DN355 against the RFP General Piping Requirements, and the power and control supply for the motorised valve | C86: This assessment. | H86: Not yet requested
A87: 13 | B87: Basis on which a third-party factory acceptance test is being arranged (PQD, ITP, procedure and inspector CV submitted 26 to 28-Sep-2026): whether instructed by the Engineer or the Contractor's own quality plan | C87: This assessment. | H87: Not yet requested
A89: ="Conclusion: the submission does not discharge the Contractor's obligation to substantiate its quantities and rates. The assessment stands at SAR " & TEXT(Assessment!K21,"#,##0.00") & " excluding VAT against the Contractor's proposal of SAR " & TEXT(Assessment!F21,"#,##0.00") & " excluding VAT." -> Conclusion: the submission does not discharge the Contractor's obligation to substantiate its quantities and rates. The assessment stands at SAR 6,984,428.39 excluding VAT against the Contractor's proposal of SAR 8,110,296.62 excluding VAT.
A91: 8. THE CONTRACTOR'S PROGRAMME DOCUMENTS OF 29-SEP-2026 AS EVIDENCE
A92: The programme is cost-loaded to the proposal value: the Contractor has spread SAR 8,110,296.62 including Overhead and Profit across its activities for progress measurement. That spread is the Contractor's own allocation of the sums claimed; it is evidence of how the Contractor intends to apply for payment against each activity, not evidence of the cost of any activity or of where any part of a lump sum sits. It is recorded here against the claimed and assessed amounts for that reason only.
A93: Item | B93: Programme section (as named) | C93: Activities | E93: Claimed by the Contractor (SAR) | F93: Loaded in the programme, incl. 5% OHP (SAR) | G93: Loaded, net of 5% OHP (SAR) | H93: Note
A94: 1 | B94: Mobilization (manpower and equipment; welfare facilities; project deliverables and submittals) and Demobilization and Closeout | C94: QCD18TSEMOB1040 to 1250; QCD18TSEDMOB1020 | E94: =Assessment!$F$8 -> 680000 | F94: 714000 | G94: =ROUND(F94/1.05,2) -> 680000 | H94: Equals Item 1 x 1.05 exactly. Site establishment and welfare are loaded on the 5-day mobilisation activities (22 to 26-Aug-2026), so the Contractor will apply for the whole of Item 1 except SAR 50,000.00 on mobilisation
A95: 2 | B95: Engineering - Shop Drawings | C95: QCD18TSEENG1240 and 1250 | E95: =Assessment!$F$10 -> 85000 | F95: 89250 | G95: =ROUND(F95/1.05,2) -> 85000 | H95: Equals Item 2 x 1.05 exactly
A96: 3, 4 | B96: Construction - Dismantling of Existing TSE Tank; Survey and Levelling | C96: QCD18TSECONDSM1020 to 1040; QCD18TSECONSL1050 | E96: =Assessment!$F$12+Assessment!$F$13 -> 81500 | F96: 85575 | G96: =ROUND(F96/1.05,2) -> 81500 | H96: Equals Items 3 and 4 x 1.05 exactly
A97: 5 to 8 | B97: Procurement (long-lead and short-lead items), Construction - TSE Tank 01 and 02, Testing and Commissioning, Tie-in Interface | C97: QCD18TSEPRC1060 to 1210; QCD18TSECONT1 and CONT2 series; QCD18TSECONTCT12050 and CT22030; QCD18TSECONTC2040 | E97: =Assessment!$F$14+Assessment!$F$16+Assessment!$F$17+Assessment!$F$18 -> 6877592 | F97: 7221471.6 | G97: =ROUND(F97/1.05,2) -> 6877592 | H97: Equals Items 5 to 8 x 1.05 exactly. Item 5 (temporary works) is not loaded on any mobilisation activity: it is spread into the tank erection activities, which is consistent with plant and attendance being consumed by erection, not by the whole site period
A98: 7 | B98: Within Items 5 to 8 above: Construction - Testing and Commissioning (both tanks) | C98: QCD18TSECONTCT12050 and CT22030 | E98: =Assessment!$F$17 -> 426400 | F98: 200305.97 | G98: =ROUND(F98/1.05,2) -> 190767.59 | H98: The Contractor's allocation to testing and commissioning is less than half of its Item 7 claim; the balance of Item 7 is not identifiable within the loading of the erection and tie-in activities. Recorded as the Contractor's own valuation of the testing activity, not as a cost
B99: Total loaded | F99: =SUM(F94:F97) -> 8110296.6 | G99: =ROUND(F99/1.05,2) -> 7724092 | H99: Equals the proposal of SAR 8,110,296.62 including Overhead and Profit
A101: Cash flow as submitted (workbook 'SAMA-D18 -THS-TSE - Cost S-Curves Cash Flow Manpower Histogram.xlsx', sheet 'Cash Flow - MN'). August carries the purchase order for the tanks (SAR 348,110.34) and the start of manufacturing: value the Contractor expects to draw before anything is installed. The payment stance for these works is no advance, no payment on account and no material on site, with tank works paid on installation and successful testing; the cash flow is recorded, not adopted, and the point is for certification, not for this assessment.
B102: Month | C102: Monthly (SAR) | E102: Cumulative (SAR) | H102: Note
B103: Jul-2026 | C103: 12035.96 | E103: =SUM($C$103:C103) -> 12035.96 | H103: Submittals
B104: Aug-2026 | C104: 1470052.2 | E104: =SUM($C$103:C104) -> 1482088.2 | H104: Mobilisation, welfare, purchase order and manufacturing
B105: Sep-2026 | C105: 1005870.6 | E105: =SUM($C$103:C105) -> 2487958.8 | H105: Dismantling, base-panel delivery and Tank 1 base
B106: Oct-2026 | C106: 2701160.7 | E106: =SUM($C$103:C106) -> 5189119.5 | H106: Deliveries and erection of both tanks
B107: Nov-2026 | C107: 2417025.3 | E107: =SUM($C$103:C107) -> 7606144.8 | H107: Erection and mechanical works
B108: Dec-2026 | C108: 504151.86 | E108: =SUM($C$103:C108) -> 8110296.6 | H108: Tie-in, testing, demobilisation
B109: Total | C109: =SUM(C103:C108) -> 8110296.6 | H109: Equals the proposal within one halala of rounding
A111: Direct manpower histogram as submitted (same workbook, sheet 'MP-HST-WK'): 16 weeks of labour on site, week ending 28-Aug to week ending 11-Dec-2026; 221 man-weeks in total, 136 skilled and 85 helpers; peak 35 in the week ending 30-Oct-2026 when the Tank 1 walls and bracing overlap the Tank 2 base. The workbook does not say whose labour it is. The tank supplier's price under Item 6 includes installation and requires 4 to 6 helpers from the Contractor; if the histogram includes the supplier's erection crews it cannot support the Contractor's Items 1, 5 or 7, and if it is the Contractor's own labour, 136 skilled man-weeks on a job whose erection is subcontracted are unexplained. Until the Contractor answers (Section 7, item 10), the histogram is used only as evidence of the 16-week labour window, which sits inside the works period carried.
...

Sheet Programme
A1: THE CONTRACTOR'S PROGRAMME - ACTIVITY DATA AND DURATION BASES
A2: TSE Irrigation Storage Tanks and Associated Pipeworks (RFP-027) - Contract QPMO-410-CT-05958
A3: Contractor: SAMA Construction | Engineer: KEO | Cost Consultant: WT Partnership | Rev 02, 30-Sep-2026
A4: How to read this tab: Section 1 records the status of the programme and of the instruction. Section 2 is the working calendar taken from the programme file. Section 3 sets the programme's windows as submitted beside the basis carried, every date derived by formula from the activity data in Section 7. Section 4 is the resource matrix: for each phase, what material is on site, which activities are active and what they depend on, whose crew does the work, which Contractor helpers, plant and site staff are needed, and where each is priced. Section 5 lists each 'Build-Up' line whose quantity is taken from this tab, with the programme exactly as submitted beside the basis carried; the carried quantity is the one linked into column D of the 'Build-Up' tab. Section 6 links every 'Build-Up' line to its activities or site service. All amounts exclude VAT.
A6: 1. STATUS OF THE PROGRAMME AND OF THE INSTRUCTION
A7: Programme: baseline schedule 'QC05958-BSL01THF-TSE-Final' (QC05958-BSL01THF-TSE.xer, data date 01-Jul-2026, 81 activities, cost-loaded to the proposal value of SAR 8,110,296.62 including 5 per cent Overhead and Profit), submitted by the Contractor to the Engineer on 12-Sep-2026 and issued to the Cost Consultant on 29-Sep-2026 with a cost S-curve, a monthly cash flow, a weekly direct-manpower histogram and a two-week look-ahead (data date 28-Sep-2026). Status at 30-Sep-2026: under the Engineer's approval process - returned as acceptable with minor comments, a procurement schedule being required; not approved. The programme is therefore evidence of the Contractor's intended sequence and durations, not an agreed basis; every line on the 'Build-Up' tab that relies on it says so.
A8: Instruction: the Contractor has been instructed to proceed and is on site (the existing tank is dismantled and the Tank 1 base panels are being received). The instruction reference and date have not been supplied to the Cost Consultant and are to be recorded on the 'Project Info' tab when received. RFP-027 dated 28-Jun-2026 stated that it was not itself an instruction to proceed. The instruction affects entitlement and the certification route, not the assessed value.
A9: Use made of the programme: (i) the site period is taken as submitted, its end being governed by the external milestone 'SAJCO Readiness for Tie-In Connections' on 03-Dec-2026 and the tie-in, sequential testing, commissioning and demobilisation that follow it; (ii) the erection windows and their durations are taken as submitted, and the labour and plant that attend them are assessed for those durations (Section 4); (iii) testing is carried on the Engineer's basis of 30-Aug-2026 (one tank filled, water re-used for the second), fitted to the submitted dates. Slippage against the baseline shown in the look-ahead (Tank 1 base panels forecast to start 30-Sep-2026 against 12-Sep-2026 programmed) is delivery-driven and adds nothing to the assessment. Dates after the look-ahead data date of 28-Sep-2026 are forecasts, not actuals.
A11: 2. WORKING CALENDAR
A12: Ref | B12: Calendar item | C12: Value | I12: Source
A13: C1 | B13: Working week for site activities | C13: 6 days, Friday non-working, 10 hours a day | I13: Calendar 'QIC 6 Days 10 Hrs' in QC05958-BSL01THF-TSE.xer, applied to every site activity; the approval activities use 'QIC 5 Days 10 Hrs' and the milestones 'QIC 7 Days 10 Hrs'
A14: C2 | B14: Non-working day within the works period | C14: 46288 | I14: Calendar exception in QC05958-BSL01THF-TSE.xer (Saudi National Day). Every working-day formula on this tab excludes Fridays and this date
A15: C3 | B15: Calendar days per month used to convert periods to months | C15: 30.4 | I15: Average month (365 days / 12); months are rounded to one decimal place
A17: 3. PROGRAMME WINDOWS - A: AS SUBMITTED; B: AS CARRIED (SUBMITTED ERECTION DATES, SEQUENTIAL TESTING)
A18: Column A reproduces the submitted programme, including its parallel testing. Column B is the basis carried: the erection dates exactly as submitted - no activity is compressed - with the Engineer's sequential testing fitted after the tank each test needs, and demobilisation following completion. Both columns are derived by formula from the activity data in Section 6 and the calendar in Section 2. The resources that each window carries are assessed in Section 4; the site period is set by the external readiness milestone of 03-Dec-2026 and the tie-in, testing, commissioning and demobilisation that follow it.
A19: Ref | B19: Window | C19: Start - Basis A | D19: Finish - Basis A | E19: Days - A | F19: Start - Basis B | G19: Finish - Basis B | H19: Days - B | I19: Derivation and source
A20: P1 | B20: Mobilisation and site establishment (calendar days) | C20: =$C$368 -> 46256 | D20: =$D$369 -> 46260 | E20: =D20-C20+1 -> 5 | F20: =C20 -> 46256 | G20: =D20 -> 46260 | H20: =E20 -> 5 | I20: Activities QCD18TSEMOB1240 and QCD18TSEMOB1250, 22 to 26-Aug-2026, QC05958-BSL01THF-TSE.xer. Mobilisation has taken place (the existing tank is dismantled)
A21: P2 | B21: Dismantling of the existing damaged Tank-1 (calendar days) | C21: =$C$371 -> 46261 | D21: =$D$374 -> 46277 | E21: =D21-C21+1 -> 17 | F21: =C21 -> 46261 | G21: =D21 -> 46277 | H21: =E21 -> 17 | I21: Activities QCD18TSECONDSM1020 to 1030, 27-Aug to 12-Sep-2026, QC05958-BSL01THF-TSE.xer. Complete per the look-ahead of 29-Sep-2026 (data date 28-Sep-2026); the completion date is not recorded, so the programmed dates are kept. Dismantling, segregation and loading are within the Item 3 quotation
A22: P3 | B22: Tank 1 - base panels (working days) | C22: =$C$380 -> 46277 | D22: =$D$380 -> 46300 | E22: =NETWORKDAYS.INTL(C22,D22,"0000100",$C$14) -> 20 | F22: =C22 -> 46277 | G22: =D22 -> 46300 | H22: =E22 -> 20 | I22: Activity QCD18TSECONT1INS1020, 12-Sep to 05-Oct-2026, 20 working days, linked to the partial delivery QCD18TSEPRC1120 (08-Sep to 03-Oct-2026, start 3 days after, finish 2 days after). Taken as submitted. The identical work on Tank 2 (QCD18TSECONT2INS1020) is programmed at 6 working days - a productivity cross-check only (Section 4, S5). The look-ahead forecasts the start as 30-Sep-2026, delivery-driven, the Contractor's risk
A23: P4 | B23: Tank 1 - wall panels (working days) | C23: =$C$386 -> 46301 | D23: =$D$386 -> 46319 | E23: =NETWORKDAYS.INTL(C23,D23,"0000100",$C$14) -> 16 | F23: =C23 -> 46301 | G23: =D23 -> 46319 | H23: =E23 -> 16 | I23: Activity QCD18TSECONT1INS1030, 06 to 24-Oct-2026, 16 working days, linked to the wall-panel delivery QCD18TSEPRC1170 (start 2 days after, finish 4 days after). Taken as submitted; Tank 2 walls (QCD18TSECONT2INS1030) 12 working days, cross-check only
A24: P5 | B24: Tank 1 - bracing (working days) | C24: =$C$387 -> 46303 | D24: =$D$387 -> 46324 | E24: =NETWORKDAYS.INTL(C24,D24,"0000100",$C$14) -> 19 | F24: =C24 -> 46303 | G24: =D24 -> 46324 | H24: =E24 -> 19 | I24: Activity QCD18TSECONT1INS1060, 08 to 29-Oct-2026, 19 working days, starting 2 days after the walls and finishing 5 days after them. Taken as submitted; Tank 2 bracing 15 working days, cross-check only
A25: P6 | B25: Tank 1 - roof supports and ladder (working days) | C25: =$C$393 -> 46326 | D25: =$D$393 -> 46330 | E25: =NETWORKDAYS.INTL(C25,D25,"0000100",$C$14) -> 5 | F25: =C25 -> 46326 | G25: =D25 -> 46330 | H25: =E25 -> 5 | I25: Activity QCD18TSECONT1INS1040, 31-Oct to 04-Nov-2026, 5 working days, the same as Tank 2
A26: P7 | B26: Tank 1 - roof panels (working days) | C26: =$C$397 -> 46331 | D26: =$D$397 -> 46337 | E26: =NETWORKDAYS.INTL(C26,D26,"0000100",$C$14) -> 6 | F26: =C26 -> 46331 | G26: =D26 -> 46337 | H26: =E26 -> 6 | I26: Activity QCD18TSECONT1INS1050, 05 to 11-Nov-2026, 6 working days, the same as Tank 2
A27: Ref | B27: Window | C27: Start - Basis A | D27: Finish - Basis A | E27: Days - A | F27: Start - Basis B | G27: Finish - Basis B | H27: Days - B | I27: Derivation and source
A28: P8 | B28: Tank 1 - mechanical works: nozzles, level transmitter, pipes and fittings (working days) | C28: =$C$398 -> 46335 | D28: =$D$400 -> 46342 | E28: =NETWORKDAYS.INTL(C28,D28,"0000100",$C$14) -> 7 | F28: =C28 -> 46335 | G28: =D28 -> 46342 | H28: =E28 -> 7 | I28: Activities QCD18TSECONT1MW2050, 2060 and 2055, 09 to 16-Nov-2026. Nozzles and internals are within the supplier's scope (Item 6); the level transmitter and the pipes and fittings are priced supplied and installed under Item 8
A29: P9 | B29: Tank 2 - base panels (working days) | C29: =$C$390 -> 46317 | D29: =$D$390 -> 46323 | E29: =NETWORKDAYS.INTL(C29,D29,"0000100",$C$14) -> 6 | F29: =C29 -> 46317 | G29: =D29 -> 46323 | H29: =E29 -> 6 | I29: Activity QCD18TSECONT2INS1020, 22 to 28-Oct-2026, 6 working days, starting 2 working days after the Tank 2 delivery begins (QCD18TSEPRC1210, 20-Oct-2026); from here the two tanks are erected on two fronts at once until 17-Nov-2026
A30: P10 | B30: Tank 2 - wall panels (working days) | C30: =$C$392 -> 46324 | D30: =$D$392 -> 46337 | E30: =NETWORKDAYS.INTL(C30,D30,"0000100",$C$14) -> 12 | F30: =C30 -> 46324 | G30: =D30 -> 46337 | H30: =E30 -> 12 | I30: Activity QCD18TSECONT2INS1030, 29-Oct to 11-Nov-2026, 12 working days
A31: P11 | B31: Tank 2 - bracing (working days) | C31: =$C$394 -> 46327 | D31: =$D$394 -> 46343 | E31: =NETWORKDAYS.INTL(C31,D31,"0000100",$C$14) -> 15 | F31: =C31 -> 46327 | G31: =D31 -> 46343 | H31: =E31 -> 15 | I31: Activity QCD18TSECONT2INS1060, 01 to 17-Nov-2026, 15 working days
A32: P12 | B32: Tank 2 - roof supports and ladder (working days) | C32: =$C$401 -> 46344 | D32: =$D$401 -> 46349 | E32: =NETWORKDAYS.INTL(C32,D32,"0000100",$C$14) -> 5 | F32: =C32 -> 46344 | G32: =D32 -> 46349 | H32: =E32 -> 5 | I32: Activity QCD18TSECONT2INS1040, 18 to 23-Nov-2026, 5 working days
A33: P13 | B33: Tank 2 - roof panels (working days) | C33: =$C$402 -> 46350 | D33: =$D$402 -> 46356 | E33: =NETWORKDAYS.INTL(C33,D33,"0000100",$C$14) -> 6 | F33: =C33 -> 46350 | G33: =D33 -> 46356 | H33: =E33 -> 6 | I33: Activity QCD18TSECONT2INS1050, 24 to 30-Nov-2026, 6 working days
A34: P14 | B34: Tank 2 - mechanical works: nozzles, level transmitter, pipes and fittings (working days) | C34: =$C$403 -> 46354 | D34: =$D$405 -> 46359 | E34: =NETWORKDAYS.INTL(C34,D34,"0000100",$C$14) -> 6 | F34: =C34 -> 46354 | G34: =D34 -> 46359 | H34: =E34 -> 6 | I34: Activities QCD18TSECONT2MW2030, 2040 and 2020, 28-Nov to 03-Dec-2026
A35: P15 | B35: Milestone - SAJCO readiness for the tie-in connections (external) | C35: =$C$406 -> 46359 | D35: =$D$406 -> 46359 | E35: - | F35: =C35 -> 46359 | G35: =D35 -> 46359 | H35: - | I35: Activity QCD18TSECONIF2050, 03-Dec-2026, zero duration. An interface milestone outside the Contractor's control, taken as submitted on both bases; it, not the tank erection, fixes the earliest tie-in date
A36: P16 | B36: Tie-in connections with the existing pump room (working days) | C36: =$C$407 -> 46361 | D36: =$D$407 -> 46364 | E36: =NETWORKDAYS.INTL(C36,D36,"0000100",$C$14) -> 4 | F36: =C36 -> 46361 | G36: =D36 -> 46364 | H36: =E36 -> 4 | I36: Activity QCD18TSECONTC2040, 05 to 08-Dec-2026, 4 working days, following the readiness milestone
A37: P17 | B37: Testing and commissioning as programmed - both tanks in parallel (working days) | C37: =$C$408 -> 46365 | D37: =$D$409 -> 46372 | E37: =NETWORKDAYS.INTL(C37,D37,"0000100",$C$14) -> 7 | F37: - | G37: - | H37: - | I37: Basis A only: activities QCD18TSECONTCT12050 and QCD18TSECONTCT22030, 09 to 16-Dec-2026, 7 working days each, in parallel, with two simultaneous fills. Not carried: the Engineer's (KEO) email of 30-Aug-2026 states that installation and testing will not be in parallel and that one tank is filled and the water re-used for the second. The sequential, task-based sequence carried is at P18 to P22
A38: P18 | B38: Hydrostatic test - Tank 1, before the tie-in (working days) | C38: =G37 -> - | D38: =G37 -> - | E38: =G37 -> - | F38: =WORKDAY.INTL(D28,1,"0000100",$C$14) -> 46343 | G38: =WORKDAY.INTL(F38,H38-1,"0000100",$C$14) -> 46350 | H38: =$E$408 -> 7 | I38: Carried basis: starts the working day after the Tank 1 mechanical works (submitted date) and takes the 7 working days the Contractor programmed per tank. Elapsed sequence assumed within those 7 days: tankered filling about 5 working days, the 24-hour hold (unattended apart from level readings), inspection of joints and nozzles and records 1 day. The fill rate is an assumption, not a measured throughput: 3,774 m3 in 5 days needs about 750 m3 a day, for example two 30 m3 tankers on about 12 round trips each, which depends on the water source the Employer has yet to confirm; if the source is further away the elapsed time lengthens but the attendance does not. Attendance: the QA/QC inspector (1.3, monthly) and the commissioning engineer for one day at the end of the hold (7.13); the supplier's leak-test supervision is within Item 6. It sits inside the 15 working days of float the programme gives Tank 1 (17 to 24-Nov-2026). Conditional on an Engineer-approved method: internals flushed and nozzles blind-flanged (RFP Scope of Works work packages 4 and 5), the water retained in Tank 1 until Tank 2 is ready, losses at 'Build-Up' line 7.5
A39: P19 | B39: Transfer of the test water from Tank 1 to Tank 2 (working days) | C39: =G37 -> - | D39: =G37 -> - | E39: =G37 -> - | F39: =WORKDAY.INTL(MAX(G38,G34),1,"0000100",$C$14) -> 46361 | G39: =WORKDAY.INTL(F39,H39-1,"0000100",$C$14) -> 46363 | H39: 3 | I39: Starts the working day after both the Tank 1 test has passed (P18) and Tank 2 is ready to receive water (mechanical works complete, P14, interior flushed). Pumped tank to tank through temporary hoses with the outlet valves isolated; the tie-in is not needed for the transfer. 3 working days is an assessed assumption pending the Contractor's method statement: 3,774 m3 at about 130 m3 an hour over 10-hour shifts, a 150 mm self-priming diesel pump against a low head (adjacent tanks at one level, about 4 m static plus hose friction) - 'Build-Up' lines 7.2 to 7.4
A40: P20 | B40: Hydrostatic test - Tank 2, after the transfer (working days) | C40: =G37 -> - | D40: =G37 -> - | E40: =G37 -> - | F40: =WORKDAY.INTL(G39,1,"0000100",$C$14) -> 46364 | G40: =WORKDAY.INTL(F40,H40-1,"0000100",$C$14) -> 46368 | H40: 4 | I40: Elapsed: the Tank 2 test sequence is 7 working days from the start of the transfer, the same as the programme's per-tank figure - 3 days of transfer (P19, attended by the transfer labour at 7.4), then 4 days here: top-up to test level (1), the 24-hour hold (1, unattended apart from level readings), inspection of joints and nozzles and records (2). Attendance as for P18. Assessed assumption
A41: P21 | B41: Component and subsystem checks after the tie-in - instruments, nozzles, valves, ladders; tank-pump-network interfaces (working days) | C41: =G37 -> - | D41: =G37 -> - | E41: =G37 -> - | F41: =WORKDAY.INTL(G36,1,"0000100",$C$14) -> 46365 | G41: =WORKDAY.INTL(F41,H41-1,"0000100",$C$14) -> 46368 | H41: 3 | I41: RFP Scope of Works 5.2, component testing and subsystem validation. Follows the tie-in and may overlap the Tank 2 hydrostatic test, because these checks do not need both tanks in service. 3 working days is an assessed assumption, not a programme figure: the Contractor's programme has no separate activity for this stage (its two 7-working-day 'Testing & Commissioning' activities cover the hydrostatic test and the commissioning of each tank together). Staffing at 'Build-Up' lines 7.13 to 7.18
A42: P21b | B42: Integrated system commissioning - full operational demonstration and witness testing (working days) | C42: =G37 -> - | D42: =G37 -> - | E42: =G37 -> - | F42: =WORKDAY.INTL(MAX(G36,G40,G41),1,"0000100",$C$14) -> 46369 | G42: =WORKDAY.INTL(F42,H42-1,"0000100",$C$14) -> 46371 | H42: 3 | I42: RFP Scope of Works 5.2, integrated system commissioning. Starts the working day after the last of the tie-in (P16), the Tank 2 hydrostatic test (P20) and the component checks (P21): both tanks must have passed and be connected before full operation is demonstrated. 3 working days (pump interface run, network demonstration, witnessed test and records) is an assessed assumption on the same footing as P21
A43: P22 | B43: Completion of testing and commissioning - both tanks | C43: =$D$410 -> 46372 | D43: =C43 -> 46372 | E43: - | F43: =G42 -> 46371 | G43: =F43 -> 46371 | H43: - | I43: A: completion milestones QCD18TSEOMS1040 and 1050, 16-Dec-2026, with parallel testing. B: end of the integrated system commissioning, conditional on the Tank 1 test preceding the tie-in (P18); if it cannot, see sensitivity S2
A44: P23 | B44: Demobilisation, as-built drawings and close-out documents (working days) | C44: =$C$412 -> 46373 | D44: =$D$412 -> 46380 | E44: =NETWORKDAYS.INTL(C44,D44,"0000100",$C$14) -> 7 | F44: =WORKDAY.INTL(G43,1,"0000100",$C$14) -> 46372 | G44: =WORKDAY.INTL(F44,H44-1,"0000100",$C$14) -> 46379 | H44: =E44 -> 7 | I44: Activities QCD18TSEDMOB1020 and QCD18TSEDMOB3020, 17 to 24-Dec-2026, 7 working days in parallel. B follows the completion of testing (P22)
A45: Ref | B45: Window | C45: Start - Basis A | D45: Finish - Basis A | E45: Days - A | F45: Start - Basis B | G45: Finish - Basis B | H45: Days - B | I45: Derivation and source
B46: Derived periods used in Sections 4 and 5
A47: D1 | B47: Site period - mobilisation start to demobilisation finish (calendar days) | C47: =C20 -> 46256 | D47: =D44 -> 46380 | E47: =D47-C47+1 -> 125 | F47: =F20 -> 46256 | G47: =G44 -> 46379 | H47: =G47-F47+1 -> 124 | I47: The continuous site establishment runs for this period: welfare cabins, WC, water tank and deliveries, the 30 kVA welfare generator, the site pick-up, workforce transport and the watchman, and the site staff whose duties cover the demobilisation week (Section 4, roles). A: the programme as submitted, 22-Aug to 24-Dec-2026. B: the same erection dates with the sequential testing carried, conditional on the early Tank 1 test (P18). The site engineer's 3 close-out days at 'Build-Up' line 1.22 fall after this period and are intentionally off-site visits, not a second allowance
A48: D2 | B48: Works period - mobilisation start to completion of testing and commissioning (calendar days) | C48: =C20 -> 46256 | D48: =D43 -> 46372 | E48: =D48-C48+1 -> 117 | F48: =F20 -> 46256 | G48: =G43 -> 46371 | H48: =G48-F48+1 -> 116 | I48: The daytime 100 kVA works generator runs for this period; no works power is needed during demobilisation, when the welfare generator alone continues
A49: D3 | B49: Erection window - Tank 1 base panels start to Tank 2 mechanical finish (calendar days) | C49: =C22 -> 46277 | D49: =D34 -> 46359 | E49: =D49-C49+1 -> 83 | F49: =C49 -> 46277 | G49: =D49 -> 46359 | H49: =E49 -> 83 | I49: Power tools and lighting towers are hired by the month while erection is in progress, 12-Sep to 03-Dec-2026 as submitted; the same on both bases
A50: D6 | B50: Access equipment window - Tank 1 walls start to Tank 2 roof finish (calendar days) | C50: =C23 -> 46301 | D50: =D33 -> 46356 | E50: =D50-C50+1 -> 56 | F50: =C50 -> 46301 | G50: =D50 -> 46356 | H50: =E50 -> 56 | I50: Mobile access towers and podium steps are hired by the month for the period the walls, bracing and roofs are worked on; rounded up to whole months at 'Build-Up' lines 5.4 and 5.6
A51: D7 | B51: Storage containers window - first panels on site to last roof panel installed (calendar days) | C51: =$C$377 -> 46273 | D51: =D33 -> 46356 | E51: =D51-C51+1 -> 84 | F51: =C51 -> 46273 | G51: =D51 -> 46356 | H51: =E51 -> 84 | I51: First delivery 08-Sep-2026 to the Tank 2 roof finish 30-Nov-2026. Panels have to be stored from the first delivery whatever the erection pace; storage is priced by the container-month, so the delivery staging adds no separate cost here
B52: Sensitivity - not carried; same durations and dependencies as P18 to P23
A53: S2 | B53: Carried basis if the Tank 1 test cannot precede the tie-in - Tank 1 test after the tie-in, transfer, Tank 2 test, integrated commissioning, demobilisation (calendar days from mobilisation) | C53: =F20 -> 46256 | D53: =WORKDAY.INTL(WORKDAY.INTL(WORKDAY.INTL(WORKDAY.INTL(MAX(G36,WORKDAY.INTL(WORKDAY.INTL(WORKDAY.INTL(WORKDAY.INTL(WORKDAY.INTL(WORKDAY.INTL(G36,1,"0000100",$C$14),7-1,"0000100",$C$14),1,"0000100",$C$14),3-1,"0000100",$C$14),1,"0000100",$C$14),4-1,"0000100",$C$14),WORKDAY.INTL(WORKDAY.INTL(G36,1,"0000100",$C$14),3-1,"0000100",$C$14)),1,"0000100",$C$14),3-1,"0000100",$C$14),1,"0000100",$C$14),7-1,"0000100",$C$14) -> 46392 | E53: =D53-C53+1 -> 137 | F53: - | G53: - | H53: - | I53: Tank 1 test 09 to 16-Dec-2026; transfer 17 to 20-Dec; Tank 2 test 21 to 24-Dec; component checks 09 to 12-Dec in parallel; integrated commissioning 26 to 28-Dec-2026; demobilisation 29-Dec-2026 to 05-Jan-2027 (Fridays excluded). The additional site days against D1 are shown at S3
A54: S3 | B54: S2 - complete incremental amount, excluding Overhead and Profit (first column: additional site days; third column: SAR) | C54: =E53-H47 -> 13 | D54: - | E54: =D113*(ROUND((H47+C54)/$C$15,1)-G113)+D114*(ROUND((H47+C54)/$C$15,1)-G114)+D115*(ROUND((WORKDAY.INTL(WORKDAY.INTL(MAX(G36,WORKDAY.INTL(WORKDAY.INTL(WORKDAY.INTL(WORKDAY.INTL(WORKDAY.INTL(WORKDAY.INTL(G36,1,"0000100",$C$14),7-1,"0000100",$C$14),1,"0000100",$C$14),3-1,"0000100",$C$14),1,"0000100",$C$14),4-1,"0000100",$C$14),WORKDAY.INTL(WORKDAY.INTL(G36,1,"0000100",$C$14),3-1,"0000100",$C$14)),1,"0000100",$C$14),3-1,"0000100",$C$14)-F21+1)/$C$15,1)-G115)+D116*(ROUND((H47+C54)/$C$15,1)-G116)+D117*(ROUND((WORKDAY.INTL(WORKDAY.INTL(MAX(G36,WORKDAY.INTL(WORKDAY.INTL(WORKDAY.INTL(WORKDAY.INTL(WORKDAY.INTL(WORKDAY.INTL(G36,1,"0000100",$C$14),7-1,"0000100",$C$14),1,"0000100",$C$14),3-1,"0000100",$C$14),1,"0000100",$C$14),4-1,"0000100",$C$14),WORKDAY.INTL(WORKDAY.INTL(G36,1,"0000100",$C$14),3-1,"0000100",$C$14)),1,"0000100",$C$14),3-1,"0000100",$C$14)-$C$377+1)/$C$15,1)-G117)+D118*(ROUND((H47+C54)/$C$15,1)-G118)+D119*(ROUND((H47+C54)/$C$15,1)-G119)+D120*(ROUND((H47+C54)/$C$15,1)-G120)+D122*(ROUND((H47+C54)/$C$15,1)-G122)+D124*(ROUND((H47+C54)/$C$15,1)-G124)+D125*(ROUND((H47+C54)/$C$15,1)-G125)+D131*(ROUND((WORKDAY.INTL(WORKDAY.INTL(MAX(G36,WORKDAY.INTL(WORKDAY.INTL(WORKDAY.INTL(WORKDAY.INTL(WORKDAY.INTL(WORKDAY.INTL(G36,1,"0000100",$C$14),7-1,"0000100",$C$14),1,"0000100",$C$14),3-1,"0000100",$C$14),1,"0000100",$C$14),4-1,"0000100",$C$14),WORKDAY.INTL(WORKDAY.INTL(G36,1,"0000100",$C$14),3-1,"0000100",$C$14)),1,"0000100",$C$14),3-1,"0000100",$C$14)-F20+1)/$C$15,1)-G131)+D132*(ROUND((H47+C54)/$C$15,1)-G132)+D133*(ROUND((H47+C54)/$C$15,1)-G133)+D121*(2*ROUNDUP((H47+C54)/7,0)-G121) -> 32820 | F54: - | G54: - | H54: - | I54: Every Section 5 line re-evaluated with the S2 dates by its own formula and rounding: the site-period lines and site staff ('Build-Up' 1.1 to 1.8, 1.10, 1.12, 1.13, 5.8 and 5.9) at the S2 days in months; welfare-water deliveries (1.9) at two per rounded-up week; the works generator (5.7) to the S2 end of commissioning. The erection-window, plant, helper, access, container and Item 7 lines do not move because only the testing tail moves. Not carried: it applies only if the Engineer does not accept the early Tank 1 test
A55: S4 | B55: S2 - Overhead and Profit at 5 per cent on S3 (first column) and incremental amount including it (third column), SAR | C55: =ROUND(E54*0.05,2) -> 1641 | D55: - | E55: =E54+C55 -> 34461 | F55: - | G55: - | H55: - | I55: Applied once at the rate on the 'Assessment' tab. Nothing in S2 to S4 is carried into the assessment
A57: 4. RESOURCE MATRIX - LABOUR, PLANT AND SITE STAFF BY PHASE, RECONCILED TO THE 'BUILD-UP' TAB
A58: Supplier scope - recorded basis, not yet verified from the offer itself. The Contractor's Item 6 reads 'Supply and install'. The previous revision records the adopted Al Mousa quotation S04488 with the Stalwart offer SS-07-26-1516 as including erection, with the Contractor providing offloading and hoisting, scaffold, storage and handling, power and 4 to 6 non-skilled labourers. The offer is not attached to this revision, so that scope is carried provisionally on the recorded basis and is to be confirmed against the original offer; on it, GRP erectors are within Item 6 and are not priced here. The histogram names no employer or trade, so its skilled row is not treated as evidence either way ('Build-Up Comparison' tab, Section 7, item 10).
A59: Fronts and gangs. Only Tank 1 material is planned on site until the Tank 2 kit is expected (20 to 21-Oct-2026 per the tracker, 20-Oct to 04-Nov-2026 programmed - forecast dates): one erection front, one helper gang. From 22-Oct-2026 the programme runs two fronts until the Tank 1 nozzles finish on 14-Nov-2026; a second gang is carried only for that interval. Walls and bracing are one front (bracing starts 2 working days after the walls and finishes 5 after them, tier by tier), so one gang serves both. Deliveries that fall on erection days are offloaded by the gang on site for part of its shift; only deliveries before a front has opened carry extra people.
A60: Attendance basis. Helper-days are carried for the submitted durations of each activity: the gang attends the supplier's crew for as long as the crew is there. Crew production and redeployment are not evidenced, so no idle time is deducted; the Contractor's own shorter Tank 2 durations for the same work are shown as a conditional efficiency sensitivity (S5), not as a deduction. Conversions: helpers to man-months at 26 working days; plant by the working day on site; monthly hire at 30.4 calendar days, rounded to one decimal or up to whole months where hire is monthly. Nothing priced in Items 3, 7, 8 or at line 1.16 is repeated here.
A61: Ref | B61: Phase, activities and window as submitted | C61: Working days - submitted | D61: Working days - Tank 2 pace (cross-check) | E61: Helpers (No.) | F61: Helper-days carried | G61: Helper-days above Tank 2 pace - sensitivity only | H61: Boom truck days | I61: Telehandler days | J61: Crew, predecessors, basis; priced item
A62: M1 | B62: Mobilisation and site establishment, 22 to 26-Aug-2026 (P1) | C62: =NETWORKDAYS.INTL(C20,D20,"0000100",$C$14) -> 5 | D62: =C62 -> 5 | E62: 2 | F62: =C62*E62 -> 10 | G62: =(C62-D62)*E62 -> 0 | H62: 0 | I62: 0 | J62: 2 helpers setting out cabins, storage and barriers - assessed; trips at 1.14. Priced at 5.10
A63: M2 | B63: Dismantling of the existing tank, 27-Aug to 12-Sep-2026 (P2) - Contractor attendance | C63: =NETWORKDAYS.INTL(C21,D21,"0000100",$C$14) -> 14 | D63: =C63 -> 14 | E63: 2 | F63: =C63*E63 -> 28 | G63: =(C63-D63)*E63 -> 0 | H63: 0 | I63: 0 | J63: Dismantling, segregation, loading and the crane are within the Item 3 quotation (recorded scope, offer not attached). 2 helpers for the Contractor's own duties: exclusion zone and barriers, decontamination wash-down support, housekeeping of the segregation area - assessed, provisional. Priced at 5.10
A64: M3 | B64: Offloading of deliveries before a front has opened - first Tank 1 base batch (08-Sep programmed), Tank 2 kit (20 to 21-Oct forecast) | C64: 3 | D64: =C64 -> 3 | E64: 4 | F64: =C64*E64 -> 12 | G64: =(C64-D64)*E64 -> 0 | H64: 0 | I64: 0 | J64: Extra people only on these 3 days; every other delivery day (18 assumed in all: 4 + 4 + 8 + 2) is offloaded by the gang already on site for part of its shift. Truck-arrival days are an assumption pending the delivery schedule. Boom truck and telehandler on all delivery days are in the plant rows. Priced at 5.10
A65: M4 | B65: SINGLE FRONT - Tank 1 base panels, 12-Sep to 05-Oct-2026 (P3); after the base-panel delivery starts (+3 days), dismantling and survey | C65: =E22 -> 20 | D65: =$E$390 -> 6 | E65: 5 | F65: =C65*E65 -> 100 | G65: =(C65-D65)*E65 -> 70 | H65: 0 | I65: =C65 -> 20 | J65: Supplier's crew erects (Item 6, recorded). One gang of 5 helpers - midpoint of the supplier's 4 to 6, assumed per front - attends for the submitted 20 days, which the programme paces to the batched delivery (finish 2 days after it). Tank 2 does the same work in 6 days; the difference is the S5 sensitivity. Telehandler daily; no lifting plant. Priced at 5.10, 5.2
A66: M5 | B66: SINGLE FRONT - Tank 1 wall panels and bracing, 06 to 29-Oct-2026 (P4, P5 - one front); after the base and the wall-panel delivery (+2 days) | C66: =NETWORKDAYS.INTL(C23,D24,"0000100",$C$14) -> 21 | D66: =NETWORKDAYS.INTL(C30,D31,"0000100",$C$14) -> 17 | E66: 5 | F66: =C66*E66 -> 105 | G66: =(C66-D66)*E66 -> 20 | H66: =ROUND(E23/2,0)+ROUND((C66-E23)/2,0) -> 11 | I66: =E23 -> 16 | J66: One gang of 5 serves walls and bracing together for the submitted 21 days (Tank 2: 17 days - S5). Telehandler on wall days (16); boom truck alternate days for upper tiers and bracing members - assessed. Priced at 5.10, 5.1, 5.2
A67: M6 | B67: Tank 1 roof supports and ladder, 31-Oct to 04-Nov-2026 (P6); after the bracing | C67: =E25 -> 5 | D67: =C67 -> 5 | E67: 3 | F67: =C67*E67 -> 15 | G67: =(C67-D67)*E67 -> 0 | H67: =D67 -> 5 | I67: =ROUND(D67/2,0) -> 3 | J67: TWO FRONTS from 22-Oct: Tank 1 gang down to 3 (little panel handling) while the second gang is on Tank 2 (M9, M10). Priced at 5.10, 5.1, 5.2
A68: M7 | B68: Tank 1 roof panels, 05 to 11-Nov-2026 (P7); after the roof supports | C68: =E26 -> 6 | D68: =C68 -> 6 | E68: 5 | F68: =C68*E68 -> 30 | G68: =(C68-D68)*E68 -> 0 | H68: =D68 -> 6 | I68: =D68 -> 6 | J68: Tank 1 gang back to 5; boom truck and telehandler daily, concurrent with the Tank 2 walls - see the plant concurrency row. Priced at 5.10, 5.1, 5.2
A69: M8 | B69: Tank 1 nozzles and internals, 09 to 14-Nov-2026 (within P8); roof panels finish 2 days before | C69: =$E$398 -> 5 | D69: =C69 -> 5 | E69: 2 | F69: =C69*E69 -> 10 | G69: =(C69-D69)*E69 -> 0 | H69: 0 | I69: 0 | J69: 2 helpers with the supplier's fitters. The level transmitter and pipework in P8 are Item 8 supplied-and-installed lines. Priced at 5.10
A70: M9 | B70: TWO FRONTS - Tank 2 base panels, 22 to 28-Oct-2026 (P9); 2 days after the Tank 2 kit delivery starts (forecast) | C70: =E29 -> 6 | D70: =C70 -> 6 | E70: 5 | F70: =C70*E70 -> 30 | G70: =(C70-D70)*E70 -> 0 | H70: 0 | I70: =C70 -> 6 | J70: Second gang of 5: the Tank 1 gang is still on the Tank 1 walls and bracing to 29-Oct; a shared gang would hold Tank 2 until 30-Oct and push its mechanical completion past the 03-Dec-2026 readiness date. Priced at 5.10, 5.2
A71: M10 | B71: Tank 2 wall panels and bracing, 29-Oct to 17-Nov-2026 (P10, P11 - one front) | C71: =NETWORKDAYS.INTL(C30,D31,"0000100",$C$14) -> 17 | D71: =C71 -> 17 | E71: 5 | F71: =C71*E71 -> 85 | G71: =(C71-D71)*E71 -> 0 | H71: =ROUND(E30/2,0)+ROUND((C71-E30)/2,0) -> 9 | I71: =E30 -> 12 | J71: As M5, second gang. Priced at 5.10, 5.1, 5.2
A72: M11 | B72: Tank 2 roof supports and ladder, 18 to 23-Nov-2026 (P12) - single front again from 15-Nov | C72: =E32 -> 5 | D72: =C72 -> 5 | E72: 3 | F72: =C72*E72 -> 15 | G72: =(C72-D72)*E72 -> 0 | H72: =D72 -> 5 | I72: =ROUND(D72/2,0) -> 3 | J72: As M6; one gang remains. Priced at 5.10, 5.1, 5.2
A73: M12 | B73: Tank 2 roof panels, 24 to 30-Nov-2026 (P13) | C73: =E33 -> 6 | D73: =C73 -> 6 | E73: 5 | F73: =C73*E73 -> 30 | G73: =(C73-D73)*E73 -> 0 | H73: =D73 -> 6 | I73: =D73 -> 6 | J73: As M7. Priced at 5.10, 5.1, 5.2
A74: M13 | B74: Tank 2 nozzles and internals, 28-Nov to 02-Dec-2026 (within P14) | C74: =$E$403 -> 5 | D74: =C74 -> 5 | E74: 2 | F74: =C74*E74 -> 10 | G74: =(C74-D74)*E74 -> 0 | H74: 0 | I74: 0 | J74: As M8. Priced at 5.10
A75: Ref | B75: Phase, activities and window as submitted | C75: Working days - submitted | D75: Working days - Tank 2 pace (cross-check) | E75: Helpers (No.) | F75: Helper-days carried | G75: Helper-days above Tank 2 pace - sensitivity only | H75: Boom truck days | I75: Telehandler days | J75: Crew, predecessors, basis; priced item
A76: M14 | B76: Tie-in, hydrostatic tests, transfer and commissioning, 17-Nov to 15-Dec-2026 (P16, P18 to P21b) | C76: =H36+H38+H39+H40+H41+H42 -> 24 | D76: =C76 -> 24 | E76: 0 | F76: =C76*E76 -> 0 | G76: =(C76-D76)*E76 -> 0 | H76: 0 | I76: 0 | J76: No helpers here: transfer labour 7.4, disinfection labour 7.8, commissioning staff 7.13 to 7.17, pipework testing crew 8.18, tie-in 8.14 and 8.15; tankers, pump and hoses 7.1 to 7.3 and 7.22
A77: M15 | B77: Demobilisation and site clean-up, 16 to 23-Dec-2026 (P23) | C77: =H44 -> 7 | D77: =C77 -> 7 | E77: 0 | F77: =C77*E77 -> 0 | G77: =(C77-D77)*E77 -> 0 | H77: 0 | I77: 0 | J77: Site clean-up 4 No. x 3 days is line 1.16; trips 1.15
B78: Helper-days carried - 'Build-Up' line 5.10 (submitted durations, unique people, no double allocation) | F78: =SUM(F62:F77) -> 480 | J78: M1 to M13. Peak on any day: 10 (two gangs of 5, 22 to 29-Oct-2026); a gang offloading on an erection day is the same people
B79: Helper-days above the Tank 2 pace on the Tank 1 base, walls and bracing - efficiency sensitivity only, not deducted | G79: =SUM(G62:G77) -> 90 | J79: M4 and M5. Would apply only if the Tank 1 gang could have been released on the Contractor's Tank 2 durations; crew production and redeployment are not evidenced. Value at S5 in Section 5
B80: Helper man-months at 26 working days - 'Build-Up' line 5.10 quantity | F80: =ROUND(F78/26,1) -> 18.5 | J80: Conversion for the man-month rate (6-day week)
B81: Histogram as submitted: helpers 85 man-weeks (510 man-days), skilled 136 man-weeks, peak 35 in the week ending 30-Oct-2026 | F81: =85*6 -> 510 | J81: The Contractor's own helper row, for comparison only; not used to set any figure above. Employers and trades are not identified
B82: Plant-days summed by activity, M4 to M12, plus 18 delivery days for each unit | H82: =SUM(H62:H77)+18 -> 60 | I82: =SUM(I62:I77)+18 -> 90 | J82: Before allowing for one unit serving two concurrent activities; delivery days assumed 18
B83: Less days on which one unit serves two concurrent activities | H83: =H82-44 -> 16 | I83: =I82-62 -> 28 | J83: Counted on dated activity-days (submitted windows, boom truck on alternate wall and bracing days, delivery days spread through their windows): the hire days below are the number of distinct days on which either unit is needed. One unit of each is a provisional utilisation assumption - panel and pallet data, lift weights and cycle times are in no document received. Concurrent demand 29-Oct to 11-Nov-2026 (Tank 1 roof with Tank 2 walls); a second telehandler for those days is S6
B84: Plant hire days assessed - carried to 'Build-Up' lines 5.1 (boom truck) and 5.2 (telehandler) | H84: =H82-H83 -> 44 | I84: =I82-I83 -> 62 | J84: Day-rate hire on working days on site; idle days between staged deliveries are not paid
A85: Ref | B85: Week ending (histogram weeks) - activities in the assessed allocation | C85: Histogram helpers (No.) | D85: Histogram helper-days | E85: Assessed helper-days | F85: Assessed helpers a day | J85: Note
A86: W1 | B86: 28-Aug-2026 - Mobilisation; dismantling | C86: 3 | D86: =C86*6 -> 18 | E86: 12 | F86: =ROUND(E86/6,1) -> 2
A87: W2 | B87: 04-Sep-2026 - Dismantling (Item 3 crew); attendance | C87: 5 | D87: =C87*6 -> 30 | E87: 12 | F87: =ROUND(E87/6,1) -> 2
A88: W3 | B88: 11-Sep-2026 - Dismantling; survey; first base-panel batch | C88: 5 | D88: =C88*6 -> 30 | E88: 16 | F88: =ROUND(E88/6,1) -> 2.7
A89: W4 | B89: 18-Sep-2026 - Single front: Tank 1 base panels (programmed) | C89: 4 | D89: =C89*6 -> 24 | E89: 32 | F89: =ROUND(E89/6,1) -> 5.3
A90: W5 | B90: 25-Sep-2026 - Single front: Tank 1 base (first batch received 28-Sep) | C90: 4 | D90: =C90*6 -> 24 | E90: 25 | F90: =ROUND(E90/5,1) -> 5
A91: W6 | B91: 02-Oct-2026 - Single front: Tank 1 base | C91: 4 | D91: =C91*6 -> 24 | E91: 30 | F91: =ROUND(E91/6,1) -> 5
A92: W7 | B92: 09-Oct-2026 - Single front: Tank 1 walls and bracing; wall-panel batches | C92: 4 | D92: =C92*6 -> 24 | E92: 30 | F92: =ROUND(E92/6,1) -> 5
A93: W8 | B93: 16-Oct-2026 - Single front: Tank 1 walls and bracing | C93: 4 | D93: =C93*6 -> 24 | E93: 30 | F93: =ROUND(E93/6,1) -> 5
A94: W9 | B94: 23-Oct-2026 - Tank 2 kit expected 20-Oct; second front opens 22-Oct | C94: 6 | D94: =C94*6 -> 36 | E94: 43 | F94: =ROUND(E94/6,1) -> 7.2
A95: W10 | B95: 30-Oct-2026 - Two fronts: Tank 1 bracing and roof supports; Tank 2 base and walls | C95: 12 | D95: =C95*6 -> 72 | E95: 60 | F95: =ROUND(E95/6,1) -> 10
A96: W11 | B96: 06-Nov-2026 - Two fronts: Tank 1 roof; Tank 2 walls and bracing | C96: 10 | D96: =C96*6 -> 60 | E96: 50 | F96: =ROUND(E96/6,1) -> 8.3
A97: W12 | B97: 13-Nov-2026 - Two fronts: Tank 1 roof and nozzles; Tank 2 bracing; pipe delivery | C97: 8 | D97: =C97*6 -> 48 | E97: 63 | F97: =ROUND(E97/6,1) -> 10.5
A98: W13 | B98: 20-Nov-2026 - Single front: Tank 2 roof supports | C98: 6 | D98: =C98*6 -> 36 | E98: 28 | F98: =ROUND(E98/6,1) -> 4.7
A99: W14 | B99: 27-Nov-2026 - Single front: Tank 2 roof panels; Tank 1 test | C99: 5 | D99: =C99*6 -> 30 | E99: 24 | F99: =ROUND(E99/6,1) -> 4
A100: W15 | B100: 04-Dec-2026 - Tank 2 nozzles; readiness milestone | C100: 3 | D100: =C100*6 -> 18 | E100: 25 | F100: =ROUND(E100/6,1) -> 4.2
A101: W16 | B101: 11-Dec-2026 - Tie-in; transfer; Tank 2 test | C101: 2 | D101: =C101*6 -> 12 | E101: 0 | F101: =ROUND(E101/6,1) -> 0
B102: Totals - histogram helper row against the assessed allocation | D102: =SUM(D86:D101) -> 510 | E102: =SUM(E86:E101) -> 480 | J102: The assessed column places the M1 to M13 helper-days on their submitted dates and sums them by histogram week; its total equals the helper-days carried above. The Contractor's row is lower than 5 in the single-front weeks and higher in the dismantling weeks; neither difference is used to adjust the assessment
A103: Ref | B103: Site staff role and phase duties | C103: From | D103: To | E103: Calendar days | F103: Months | J103: Coverage and source; priced item
A104: R1 | B104: Site engineer - by phase: mobilisation and permits (Aug); dismantling supervision and handover records (Sep); deliveries, inspection requests and two erection fronts (Sep to Nov); tie-in, tests and commissioning coordination (Nov to Dec); demobilisation and close-out (Dec) | C104: =F47 -> 46256 | D104: =G47 -> 46379 | E104: =D104-C104+1 -> 124 | F104: =ROUND(E104/$C$15,1) -> 4.1 | J104: Dedicated for the site period D1: every phase has a duty that needs a responsible engineer present on a site outside the D-18 boundary, and no phase is quiet enough to share the role. Priced at 1.1
...

Sheet Superseded Proposal (Ref)
A1: SUPERSEDED PROPOSAL - REFERENCE ONLY
A2: Contractor's earlier proposal for 3 No. GRP tanks of 3,000 m3 each - SAR 9,149,460.00 excluding VAT
A3: Contractor: SAMA Construction | Superseded by the revised proposal SAMACO-RRFP-000001 dated 13-Aug-2026
A4: Reproduced as submitted for reference. The Engineer's RFP-027 dated 28-Jun-2026 changed the scheme to 2 No. tanks of 4,080 m3 on the existing foundations, and the revised proposal replaced this one. It is not assessed.
C5: CONTRACTOR PROPOSAL (SAMA CONSTRUCTION)
A6: Item | B6: Description | C6: Unit | D6: Qty | E6: Rate (SAR) | F6: Amount (SAR) | G6: Remarks
A7: PRELIMINARY WORK
A8: 1 | B8: Site Mobilization & Demobilization Works Site Mobilization and Demobilization of Site temporary Facilities, Welfare, Personnel, Equipment, and Resources | C8: LS | D8: 1 | E8: 816000 | F8: 816000
A9: DESIGN AND ENGINEERING
A10: 2 | B10: Site Mobilization & Demobilization Works Performing the complete design and engineering for GRP water tanks, including tank sizing, structural analysis, panel arrangement, foundation reaction loads, nozzle orientation, accessories layout, shop drawings, technical submittals and method statments in accordance with project specifications and applicable standards. | C10: LS | D10: 1 | E10: 102000 | F10: 102000
A11: SURVEY WORKS
A12: 3 | B12: Topographic survey The topographic survey includes the location, dimensions and characterization of natural and man-made elements within and around the 3rd tank area, for detailed work shall based on topographic specification | C12: LS | D12: 1 | E12: 18000 | F12: 18000
A13: 4 | B13: Geotechnical survey Carrying out the Geotechnical Investigation in accordance with QIC requirements and SBC 303 (2018), including boreholes up to 15 m depth or 3 m into competent rock, or until refusal strata (SPT N >100) is encountered (If required). The investigation shall include the required field and laboratory testing to determine soil characteristics, groundwater conditions, safe bearing capacity (SBC), settlement, and foundation recommendations for the proposed GRP water tank foundation. Testing shall include, but not be limited to, SPT, soil classification, compaction, shear strength, consolidation, chemical analysis, and rock assessment where applicable. The Geotechnical Report shall include foundation recommendations, allowable bearing capacity, settlement analysis, pile capacity assessment (if required), and all relevant geotechnical design parameters in compliance with QIC requirements and SBC 303 (2018). Trial pits shall be carried out where undisturbed sampling is not achievable, with pit depth extending at least to the proposed foundation level. | C13: LS | D13: 1 | E13: 31500 | F13: 31500
A14: EARTHWORKS
A15: 5 | B15: Site clearance with compaction Stripping and grubbing of top soil layer including bushes, grass, and/or contamination, grading and compaction for subsequent work, disposal of soil and vegetation to the designated area, inspections and Compaction tests. | C15: m² | D15: 1050 | E15: 6 | F15: 6300
A16: 6 | B16: Excavation Excavation of normal soil for general excavation, loading and transportation of excavated soil to the designated stockpile area for future re-use or directly to the backfill area within the site, protection of excavated area from debris, water, and other unsuitable material, provision of protective system for excavation slope if applicable | C16: m³ | D16: 1050 | E16: 54 | F16: 56700
A17: 7 | B17: Soil Replacement Supply, placement, and compaction of approved replacement/backfill material in layers to achieve the specified density requirements. Preparation of existing ground, including scarification and compaction prior to backfilling works. Moisture conditioning, grading, and leveling of the backfilled area to the required levels. Disposal of unsuitable/excess materials at approved designated areas. Carrying out all required inspections, field tests, laboratory tests, and quality control procedures in accordance with project specifications. | C17: m³ | D17: 1050 | E17: 60 | F17: 63000
A18: CONCRETE WORKS / REINFORCEMENT STEEL (SE)
A19: 8 | B19: Lean concrete (Sulphate Resistant Cement) Supply and placement of lean concrete including surface finishing works such as troweling, floating, edging, and brooming as required, including all necessary inspections and testing. | C19: m² | D19: 1050 | E19: 120 | F19: 126000
A20: 9 | B20: Concrete for foundation Supply and placement of reinforced concrete (RC) including concrete consolidation by vibrator, provision and installation of spacers, chamfers, and all miscellaneous items as indicated on drawings, preparation of construction joints by chipping and roughening existing concrete surfaces, surface finishing works including troweling, floating, edging, brooming, concrete curing using water or approved curing compounds including supply of curing and insulation materials such as wet blankets, hessian fabric, and curing tarpaulins, removal of concrete laitance, filling of form-tie holes with cement mortar of equivalent strength, surface preparation and moisture testing for protective coating application, including all required inspections and testing. | C20: m³ | D20: 435.3 | E20: 1920 | F20: 835776
A21: 10 | B21: Waterproofing membrane at the bottom of foundation Surface preparation of blinding concrete and supply, installation, protection, and sealing of waterproofing membrane system at bottom of foundation slabs for water-retaining structures, including all laps, joints, terminations, accessories, and related works to ensure full watertight integrity in accordance with approved drawings, project specifications, and manufacturer's recommendations; rectification of defects, protection layers, temporary works, handling, storage, and all inspections and testing necessary for complete execution, all complete as per unit rate. | C21: m² | D21: 1050 | E21: 108 | F21: 113400
A22: 11 | B22: Epoxy paint Epoxy paint above the foundations | C22: m² | D22: 1773.2 | E22: 120 | F22: 212784
A23: 12 | B23: GRP Tanks Supply, fabrication, delivery, installation, of 3,000 m³ sectional GRP panel water tank without heat insulation, with internal partition, overall tank size 30m (15m+15m) × 25m × 4m, manufactured in accordance with Korean Agency for Technology and Standards and Saudi Standards, Metrology and Quality Organization requirements, produced by MNT National Factory for Fiberglass, including all internal accessories, bolts, nuts, washers and tie rods in stainless steel grade 316, all external accessories, bolts, nuts and washers hot dip galvanized (HDG), water level indicator tube, non-toxic leak sealant, UPVC screened air vent, lockable GRP manhole, internal GRP ladder, external HDG ladder, UPVC roof panel supports, all required openings for inlet, outlet, overflow and drain connections, complete with HDG steel skid base and all necessary fittings, supports and accessories for complete operational system as per approved drawings and specifications. | C23: Unit | D23: 3 | E23: 1890000 | F23: 5670000
A24: 13 | B24: GRP Tanks testing and commissioning Testing, flushing, disinfection and commissioning of GRP water tanks including hydrostatic/watertightness testing, inspection of all panels, joints, sealants, fittings and accessories, checking of inlet, outlet, overflow and drain connections, verification of water level indicators and appurtenances, rectification of leakage if any, complete cleaning and sterilization of tank in accordance with approved specifications and authority requirements, and handing over the system in complete operational condition. | C24: Unit | D24: 3 | E24: 204000 | F24: 612000
A25: 14 | B25: Piping Connections Supply, fabrication, installation, testing and commissioning of all required piping connections for GRP water tanks including inlet, outlet, overflow, drain and interconnection piping, fittings, flanges, valves, flexible joints, supports, sleeves, accessories and connection to existing/new piping network, complete with sealing, alignment, pressure testing and all necessary works as per approved drawings and specifications. | C25: LS | D25: 1 | E25: 486000 | F25: 486000
B26: TOTAL (SAR) - VAT excluded | F26: =SUM(F8:F25) -> 9149460

Sheet Data
A1: DATA - MASTER LISTS
A2: Status | C2: Basis of Rate | E2: Assessment Outcome | G2: Contractual Basis | I2: Submission Type | K2: Revision Type
A3: Submitted | C3: BOQ Identical | E3: Accepted | G3: BOQ Item | I3: Initial Submission | K3: Rate Change
A4: Under Review | C4: BOQ Similar | E4: Not Accepted | G4: Contract Clause | I4: Revised Submission | K4: Quantity Change
A5: Query Raised | C5: Pro Rata | E5: Accepted with Qualification | G5: Specification Section | I5: Final Submission | K5: Scope Change
A6: Revised Submission | C6: Star Rate | E6: Substantiation Required | G6: CESMM4 Class/Rule | I6: Formal Claim | K6: Unit Change
A7: Assessed | C7: Market Tested | E7: Deferred | G7: NRM Rule | I7: Budget Estimate | K7: Description Change
A8: Agreed | C8: Dayworks | G8: Instruction Reference | I8: Cost Proposal | K8: New Item Added
A9: Not Agreed | C9: Provisional Sum | G9: Correspondence | K9: Item Omitted
A10: Included in Valuation | C10: Lump Sum | G10: Drawing Reference | K10: No Change
A11: Excluded | C11: Not Yet Determined | G11: Supplier Quotation
A12: Closed | G12: None
A13: Provisional
